Workbook

Sheet Information
A1: SELECTED HOUSING CHARACTERISTICS
A3: Note: The table shown may have been modified by user selections. Some information may be missing.
A5: DATA NOTES
A6: TABLE ID: | B6: DP04
A7: SURVEY/PROGRAM: | B7: American Community Survey
A8: VINTAGE: | B8: 2020
A9: DATASET: | B9: ACSDP5Y2020
A10: PRODUCT: | B10: ACS 5-Year Estimates Data Profiles
A11: UNIVERSE: | B11: None
A12: MLA: | B12: U.S. Census Bureau. "SELECTED HOUSING CHARACTERISTICS." American Community Survey, ACS 5-Year Estimates Data Profiles, Table DP04, https://data.census.gov/table/ACSDP5Y2020.DP04?q=financial+characteristics+2020&g=160XX00US0541000,1235000,4748000_310XX00US47260_3810000US440005_3910000US47492048000. Accessed on 23 Apr 2026.
A13: FTP URL: | B13: None
A14: API URL: | B14: https://api.census.gov/data/2020/acs/acs5/profile
A16: USER SELECTIONS
A17: TOPICS | B17: Financial Characteristics
A18: VINTAGES | B18: 2020
A19: GEOS | B19: Virginia Beach-Chesapeake-Norfolk, VA-NC Metro Area; Memphis city, Tennessee; Memphis city; Memphis, TN--AR--MS MSA (part); Tennessee; Arkansas (part); Little Rock--North Little Rock, AR MSA; Jacksonville city, Florida; Little Rock city, Arkansas
A21: EXCLUDED COLUMNS | B21: None
A23: APPLIED FILTERS | B23: None
A25: APPLIED SORTS | B25: None
A27: PIVOT & GROUPING
A28: PIVOT COLUMNS | B28: None
A29: PIVOT MODE | B29: Off
A30: ROW GROUPS | B30: None
A31: VALUE COLUMNS | B31: None
A33: WEB ADDRESS | B33: https://data.census.gov/table/ACSDP5Y2020.DP04?q=financial+characteristics+2020&g=160XX00US0541000,1235000,4748000_310XX00US47260_3810000US440005_3910000US47492048000
A35: TABLE NOTES
B36: Although the American Community Survey (ACS) produces population, demographic and housing unit estimates, for 2020, the 2020 Census provides the official counts of the population and housing units for the nation, states, counties, cities, and towns. For 2016 to 2019, the Population Estimates Program provides estimates of the population for the nation, states, counties, cities, and towns and intercensal housing unit estimates for the nation, states, and counties.
B37: Supporting documentation on code lists, subject definitions, data accuracy, and statistical testing can be found on the American Community Survey website in the Technical Documentation section. Sample size and data quality measures (including coverage rates, allocation rates, and response rates) can be found on the American Community Survey website in the Methodology section.
B38: Source: U.S. Census Bureau, 2016-2020 American Community Survey 5-Year Estimates
B39: Data are based on a sample and are subject to sampling variability. The degree of uncertainty for an estimate arising from sampling variability is represented through the use of a margin of error. The value shown here is the 90 percent margin of error. The margin of error can be interpreted roughly as providing a 90 percent probability that the interval defined by the estimate minus the margin of error and the estimate plus the margin of error (the lower and upper confidence bounds) contains the true value. In addition to sampling variability, the ACS estimates are subject to nonsampling error (for a discussion of nonsampling variability, see ACS Technical Documentation). The effect of nonsampling error is not represented in these tables.
B40: Households not paying cash rent are excluded from the calculation of median gross rent.
B41: Telephone service data are not available for certain geographic areas due to problems with data collection of this question that occurred in 2016 and 2019. Both ACS 1-year and ACS 5-year files were affected. It may take several years in the ACS 5-year files until the estimates are available for the geographic areas affected.
B42: The 2016-2020 American Community Survey (ACS) data generally reflect the September 2018 Office of Management and Budget (OMB) delineations of metropolitan and micropolitan statistical areas. In certain instances, the names, codes, and boundaries of the principal cities shown in ACS tables may differ from the OMB delineation lists due to differences in the effective dates of the geographic entities.
B43: Estimates of urban and rural populations, housing units, and characteristics reflect boundaries of urban areas defined based on Census 2010 data. As a result, data for urban and rural areas from the ACS do not necessarily reflect the results of ongoing urbanization.
B44: Explanation of Symbols:- The estimate could not be computed because there were an insufficient number of sample observations. For a ratio of medians estimate, one or both of the median estimates falls in the lowest interval or highest interval of an open-ended distribution.N The estimate or margin of error cannot be displayed because there were an insufficient number of sample cases in the selected geographic area. (X) The estimate or margin of error is not applicable or not available.median- The median falls in the lowest interval of an open-ended distribution (for example "2,500-")median+ The median falls in the highest interval of an open-ended distribution (for example "250,000+").** The margin of error could not be computed because there were an insufficient number of sample observations.*** The margin of error could not be computed because the median falls in the lowest interval or highest interval of an open-ended distribution.***** A margin of error is not appropriate because the corresponding estimate is controlled to an independent population or housing estimate. Effectively, the corresponding estimate has no sampling error and the margin of error may be treated as zero.
A46: COLUMN NOTES | B46: None

Sheet Table
B3: Norfolk | G3: Memphis
C4: 2020 | D4: 2024 | E4: CAGR | H4: 2020 | I4: 2024 | J4: CAGR
B5: Population | C5: =VALUE(SUBSTITUTE('Population (2020)'!E2,",","")) -> 1799674 | D5: =VALUE(SUBSTITUTE('Population (2024)'!N4,",","")) -> 1796689 | E5: =_xlfn.RRI(4,C5,D5) -> -0.00041491659 | G5: Population | H5: =VALUE(SUBSTITUTE('Population (2020)'!D2,",","")) -> 633104 | I5: =VALUE(SUBSTITUTE('Population (2024)'!J4,",","")) -> 610936 | J5: =_xlfn.RRI(4,H5,I5) -> -0.0088710426
B6: Housing Units | C6: =VALUE(SUBSTITUTE('Data (2020)'!N4,",","")) -> 739434 | D6: =VALUE(SUBSTITUTE('Data (2024)'!N4,",","")) -> 774453 | E6: =_xlfn.RRI(4,C6,D6) -> 0.011635154 | G6: Housing Units | H6: =VALUE(SUBSTITUTE('Data (2020)'!J4,",","")) -> 299599 | I6: =VALUE(SUBSTITUTE('Data (2024)'!J4,",","")) -> 291759 | J6: =_xlfn.RRI(4,H6,I6) -> -0.006607274
B7: Median Income | C7: =VALUE(SUBSTITUTE('Income (2020)'!AL17,",","")) -> 68454 | D7: =VALUE(SUBSTITUTE('Income (2024)'!AL17,",","")) -> 82402 | E7: =_xlfn.RRI(4,C7,D7) -> 0.047453448 | G7: Median Income | H7: =VALUE(SUBSTITUTE('Income (2020)'!Z17,",","")) -> 41864 | I7: =VALUE(SUBSTITUTE('Income (2024)'!Z17,",","")) -> 52679 | J7: =_xlfn.RRI(4,H7,I7) -> 0.05912983
B8: Adjusted Median Income | C8: =C7/'CPI Fred Data'!D22 -> 82968.813 | D8: =D7/'CPI Fred Data'!D26 -> 82402 | E8: =_xlfn.RRI(4,C8,D8) -> -0.001712304 | G8: Adjusted Median Income | H8: =H7/'CPI Fred Data'!D22 -> 50740.737 | I8: =I7/'CPI Fred Data'!D26 -> 52679 | J8: =_xlfn.RRI(4,H8,I8) -> 0.0094160085
B9: Av House Hold Size | C9: =VALUE('Data (2020)'!N56) -> 2.6 | D9: =VALUE('Data (2024)'!N56) -> 2.56 | E9: =_xlfn.RRI(4,C9,D9) -> -0.0038685445 | G9: Av House Hold Size | H9: =VALUE('Data (2020)'!J56) -> 2.53 | I9: =VALUE('Data (2024)'!J56) -> 2.44 | J9: =_xlfn.RRI(4,H9,I9) -> -0.00901444
B10: Owner Occupied HU | C10: =VALUE(SUBSTITUTE('Data (2020)'!N54,",","")) -> 418960 | D10: =VALUE(SUBSTITUTE('Data (2024)'!N54,",","")) -> 451287 | E10: =_xlfn.RRI(4,C10,D10) -> 0.018755733 | G10: Owner Occupied HU | H10: =VALUE(SUBSTITUTE('Data (2020)'!J54,",","")) -> 118235 | I10: =VALUE(SUBSTITUTE('Data (2024)'!J54,",","")) -> 111737 | J10: =_xlfn.RRI(4,H10,I10) -> -0.014032187
B11: Renter HU | C11: =VALUE(SUBSTITUTE('Data (2020)'!N55,",","")) -> 253093 | D11: =VALUE(SUBSTITUTE('Data (2024)'!N55,",","")) -> 266624 | E11: =_xlfn.RRI(4,C11,D11) -> 0.013105741 | G11: Renter HU | H11: =VALUE(SUBSTITUTE('Data (2020)'!J55,",","")) -> 137521 | I11: =VALUE(SUBSTITUTE('Data (2024)'!J55,",","")) -> 139093 | J11: =_xlfn.RRI(4,H11,I11) -> 0.0028455763
B12: Vacancy Rate | C12: =VALUE('Data (2020)'!N8)/100 -> 0.068 | D12: =VALUE('Data (2024)'!N8)/100 -> 0.053 | E12: =D12-C12 -> -0.015 | F12: actual change value | G12: Vacancy Rate | H12: =VALUE('Data (2020)'!J8)/100 -> 0.083 | I12: =VALUE('Data (2024)'!J8)/100 -> 0.101 | J12: =I12-H12 -> 0.018 | K12: actual change value
B13: Median Rent | C13: =VALUE(SUBSTITUTE('Data (2020)'!N152,",","")) -> 1187 | D13: =VALUE(SUBSTITUTE('Data (2024)'!N152,",","")) -> 1556 | E13: =_xlfn.RRI(4,C13,D13) -> 0.070014637 | G13: Median Rent | H13: =VALUE(SUBSTITUTE('Data (2020)'!J152,",","")) -> 915 | I13: =VALUE(SUBSTITUTE('Data (2024)'!J152,",","")) -> 1263 | J13: =_xlfn.RRI(4,H13,I13) -> 0.083915843
B14: Adjusted Median Rent | C14: =C13/'CPI Fred Data'!D22 -> 1438.6885 | D14: =D13/'CPI Fred Data'!D26 -> 1556 | E14: =_xlfn.RRI(4,C14,D14) -> 0.0197899 | G14: Adjusted Median Rent | H14: =H13/'CPI Fred Data'!D22 -> 1109.0143 | I14: =I13/'CPI Fred Data'!D26 -> 1263 | J14: =_xlfn.RRI(4,H14,I14) -> 0.033038606
B15: Median Home Value | C15: =VALUE(SUBSTITUTE('Data (2020)'!N103,",","")) -> 253800 | D15: =VALUE(SUBSTITUTE('Data (2024)'!N103,",","")) -> 363400 | E15: =_xlfn.RRI(4,C15,D15) -> 0.093889179 | G15: Median Home Value | H15: =VALUE(SUBSTITUTE('Data (2020)'!J103,",","")) -> 107100 | I15: =VALUE(SUBSTITUTE('Data (2024)'!J103,",","")) -> 209800 | J15: =_xlfn.RRI(4,H15,I15) -> 0.18305246
B16: Adjusted Median Home Value | C16: =C15/'CPI Fred Data'!D22 -> 307615.11 | D16: =D15/'CPI Fred Data'!D26 -> 363400 | E16: =_xlfn.RRI(4,C16,D16) -> 0.04254381 | G16: Adjusted Median Home Value | H16: =H15/'CPI Fred Data'!D22 -> 129809.21 | I16: =I15/'CPI Fred Data'!D26 -> 209800 | J16: =_xlfn.RRI(4,H16,I16) -> 0.12752191
B18: Jacksonville FL | G18: Little Rock
C19: 2020 | D19: 2024 | E19: CAGR | H19: 2020 | I19: 2024 | J19: CAGR
B20: Population | C20: =VALUE(SUBSTITUTE('Population (2020)'!C2,",","")) -> 949611 | D20: =VALUE(SUBSTITUTE('Population (2024)'!F4,",","")) -> 1009831 | E20: =_xlfn.RRI(4,C20,D20) -> 0.015490209 | G20: Population | H20: =VALUE(SUBSTITUTE('Population (2020)'!B2,",","")) -> 202591 | I20: =VALUE(SUBSTITUTE('Population (2024)'!B4,",","")) -> 204793 | J20: =_xlfn.RRI(4,H20,I20) -> 0.0027062916
B21: Housing Units | C21: =VALUE(SUBSTITUTE('Data (2020)'!F4,",","")) -> 389130 | D21: =VALUE(SUBSTITUTE('Data (2024)'!F4,",","")) -> 449941 | E21: =_xlfn.RRI(4,C21,D21) -> 0.036967664 | G21: Housing Units | H21: =VALUE(SUBSTITUTE('Data (2020)'!B4,",","")) -> 96399 | I21: =VALUE(SUBSTITUTE('Data (2024)'!B4,",","")) -> 99014 | J21: =_xlfn.RRI(4,H21,I21) -> 0.0067137937
B22: Median Income | C22: =VALUE(SUBSTITUTE('Income (2020)'!N17,",","")) -> 55531 | D22: =VALUE(SUBSTITUTE('Income (2024)'!N17,",","")) -> 72389 | E22: =_xlfn.RRI(4,C22,D22) -> 0.068523974 | G22: Median Income | H22: =VALUE(SUBSTITUTE('Income (2020)'!B17,",","")) -> 53620 | I22: =VALUE(SUBSTITUTE('Income (2024)'!B17,",","")) -> 66553 | J22: =_xlfn.RRI(4,H22,I22) -> 0.055504786
B23: Adjusted Median Income | C23: =C22/'CPI Fred Data'!D22 -> 67305.653 | D23: =D22/'CPI Fred Data'!D26 -> 72389 | E23: =_xlfn.RRI(4,C23,D23) -> 0.018369206 | G23: Adjusted Median Income | H23: =H22/'CPI Fred Data'!D22 -> 64989.449 | I23: =I22/'CPI Fred Data'!D26 -> 66553 | J23: =_xlfn.RRI(4,H23,I23) -> 0.0059611176
B24: Av House Hold Size | C24: =VALUE('Data (2020)'!F56) -> 2.62 | D24: =VALUE('Data (2024)'!F56) -> 2.56 | E24: =_xlfn.RRI(4,C24,D24) -> -0.0057750249 | G24: Av House Hold Size | H24: =VALUE('Data (2020)'!B56) -> 2.45 | I24: =VALUE('Data (2024)'!B56) -> 2.43 | J24: =_xlfn.RRI(4,H24,I24) -> -0.0020470936
B25: Owner Occupied HU | C25: =VALUE(SUBSTITUTE('Data (2020)'!F54,",","")) -> 196649 | D25: =VALUE(SUBSTITUTE('Data (2024)'!F54,",","")) -> 240209 | E25: =_xlfn.RRI(4,C25,D25) -> 0.051294478 | G25: Owner Occupied HU | H25: =VALUE(SUBSTITUTE('Data (2020)'!B54,",","")) -> 45625 | I25: =VALUE(SUBSTITUTE('Data (2024)'!B54,",","")) -> 47340 | J25: =_xlfn.RRI(4,H25,I25) -> 0.009267629
B26: Renter HU | C26: =VALUE(SUBSTITUTE('Data (2020)'!F55,",","")) -> 152160 | D26: =VALUE(SUBSTITUTE('Data (2024)'!F55,",","")) -> 173411 | E26: =_xlfn.RRI(4,C26,D26) -> 0.03322293 | G26: Renter HU | H26: =VALUE(SUBSTITUTE('Data (2020)'!B55,",","")) -> 37900 | I26: =VALUE(SUBSTITUTE('Data (2024)'!B55,",","")) -> 41398 | J26: =_xlfn.RRI(4,H26,I26) -> 0.022315717
B27: Vacancy Rate | C27: =VALUE('Data (2020)'!F8)/100 -> 0.066 | D27: =VALUE('Data (2024)'!F8)/100 -> 0.111 | E27: =D27-C27 -> 0.045 | F27: actual change value | G27: Vacancy Rate | H27: =VALUE('Data (2020)'!B8)/100 -> 0.12 | I27: =VALUE('Data (2024)'!B8)/100 -> 0.073 | J27: =I27-H27 -> -0.047 | K27: actual change value
B28: Median Rent | C28: =VALUE(SUBSTITUTE('Data (2020)'!F152,",","")) -> 1089 | D28: =VALUE(SUBSTITUTE('Data (2024)'!F152,",","")) -> 1568 | E28: =_xlfn.RRI(4,C28,D28) -> 0.095417172 | G28: Median Rent | H28: =VALUE(SUBSTITUTE('Data (2020)'!B152,",","")) -> 889 | I28: =VALUE(SUBSTITUTE('Data (2024)'!B152,",","")) -> 1136 | J28: =_xlfn.RRI(4,H28,I28) -> 0.06321022
B29: Adjusted Median Rent | C29: =C28/'CPI Fred Data'!D22 -> 1319.9088 | D29: =D28/'CPI Fred Data'!D26 -> 1568 | E29: =_xlfn.RRI(4,C29,D29) -> 0.044000081 | G29: Adjusted Median Rent | H29: =H28/'CPI Fred Data'!D22 -> 1077.5013 | I29: =I28/'CPI Fred Data'!D26 -> 1136 | J29: =_xlfn.RRI(4,H29,I29) -> 0.013304871
B30: Median Home Value | C30: =VALUE(SUBSTITUTE('Data (2020)'!F103,",","")) -> 187700 | D30: =VALUE(SUBSTITUTE('Data (2024)'!F103,",","")) -> 325300 | E30: =_xlfn.RRI(4,C30,D30) -> 0.14737385 | G30: Median Home Value | H30: =VALUE(SUBSTITUTE('Data (2020)'!B103,",","")) -> 172500 | I30: =VALUE(SUBSTITUTE('Data (2024)'!B103,",","")) -> 270700 | J30: =_xlfn.RRI(4,H30,I30) -> 0.11924404
B31: Adjusted Median Home Value | C31: =C30/'CPI Fred Data'!D22 -> 227499.43 | D31: =D30/'CPI Fred Data'!D26 -> 325300 | E31: =_xlfn.RRI(4,C31,D31) -> 0.093517998 | G31: Adjusted Median Home Value | H31: =H30/'CPI Fred Data'!D22 -> 209076.46 | I31: =I30/'CPI Fred Data'!D26 -> 270700 | J31: =_xlfn.RRI(4,H31,I31) -> 0.066708552

Sheet Income (2024)
B1: Little Rock city, Arkansas | N1: Jacksonville city, Florida | Z1: Memphis city, Tennessee | AL1: Virginia Beach-Chesapeake-Norfolk, VA-NC Metro Area
B2: Occupied housing units | D2: Percent occupied housing units | F2: Owner-occupied housing units | H2: Percent owner-occupied housing units | J2: Renter-occupied housing units | L2: Percent renter-occupied housing units | N2: Occupied housing units | P2: Percent occupied housing units | R2: Owner-occupied housing units | T2: Percent owner-occupied housing units | V2: Renter-occupied housing units | X2: Percent renter-occupied housing units | Z2: Occupied housing units | AB2: Percent occupied housing units | AD2: Owner-occupied housing units | AF2: Percent owner-occupied housing units | AH2: Renter-occupied housing units | AJ2: Percent renter-occupied housing units | AL2: Occupied housing units | AN2: Percent occupied housing units | AP2: Owner-occupied housing units | AR2: Percent owner-occupied housing units | AT2: Renter-occupied housing units | AV2: Percent renter-occupied housing units
A3: Label | B3: Estimate | C3: Margin of Error | D3: Estimate | E3: Margin of Error | F3: Estimate | G3: Margin of Error | H3: Estimate | I3: Margin of Error | J3: Estimate | K3: Margin of Error | L3: Estimate | M3: Margin of Error | N3: Estimate | O3: Margin of Error | P3: Estimate | Q3: Margin of Error | R3: Estimate | S3: Margin of Error | T3: Estimate | U3: Margin of Error | V3: Estimate | W3: Margin of Error | X3: Estimate | Y3: Margin of Error | Z3: Estimate | AA3: Margin of Error | AB3: Estimate | AC3: Margin of Error | AD3: Estimate | AE3: Margin of Error | AF3: Estimate | AG3: Margin of Error | AH3: Estimate | AI3: Margin of Error | AJ3: Estimate | AK3: Margin of Error | AL3: Estimate | AM3: Margin of Error | AN3: Estimate | AO3: Margin of Error | AP3: Estimate | AQ3: Margin of Error | AR3: Estimate | AS3: Margin of Error | AT3: Estimate | AU3: Margin of Error | AV3: Estimate | AW3: Margin of Error
A4: Occupied housing units | B4: 88,738 | C4: ±3,214 | D4: 88,738 | E4: ±3,214 | F4: 47,340 | G4: ±3,245 | H4: 47,340 | I4: ±3,245 | J4: 41,398 | K4: ±3,265 | L4: 41,398 | M4: ±3,265 | N4: 413,620 | O4: ±4,742 | P4: 413,620 | Q4: ±4,742 | R4: 240,209 | S4: ±6,346 | T4: 240,209 | U4: ±6,346 | V4: 173,411 | W4: ±7,223 | X4: 173,411 | Y4: ±7,223 | Z4: 250,830 | AA4: ±4,397 | AB4: 250,830 | AC4: ±4,397 | AD4: 111,737 | AE4: ±4,092 | AF4: 111,737 | AG4: ±4,092 | AH4: 139,093 | AI4: ±4,742 | AJ4: 139,093 | AK4: ±4,742 | AL4: 717,911 | AM4: ±5,455 | AN4: 717,911 | AO4: ±5,455 | AP4: 451,287 | AQ4: ±7,983 | AR4: 451,287 | AS4: ±7,983 | AT4: 266,624 | AU4: ±7,499 | AV4: 266,624 | AW4: ±7,499
A5: HOUSEHOLD INCOME IN THE PAST 12 MONTHS (IN 2024 INFLATION-ADJUSTED DOLLARS)
A6: Less than $5,000 | B6: 4,349 | C6: ±1,383 | D6: 4.9% | E6: ±1.5 | F6: 1,467 | G6: ±686 | H6: 3.1% | I6: ±1.4 | J6: 2,882 | K6: ±1,240 | L6: 7.0% | M6: ±2.9 | N6: 16,855 | O6: ±2,901 | P6: 4.1% | Q6: ±0.7 | R6: 6,668 | S6: ±1,753 | T6: 2.8% | U6: ±0.7 | V6: 10,187 | W6: ±2,196 | X6: 5.9% | Y6: ±1.3 | Z6: 17,912 | AA6: ±3,113 | AB6: 7.1% | AC6: ±1.2 | AD6: 6,346 | AE6: ±1,716 | AF6: 5.7% | AG6: ±1.5 | AH6: 11,566 | AI6: ±2,511 | AJ6: 8.3% | AK6: ±1.8 | AL6: 20,599 | AM6: ±2,324 | AN6: 2.9% | AO6: ±0.3 | AP6: 8,022 | AQ6: ±1,431 | AR6: 1.8% | AS6: ±0.3 | AT6: 12,577 | AU6: ±1,980 | AV6: 4.7% | AW6: ±0.8
A7: $5,000 to $9,999 | B7: 1,385 | C7: ±752 | D7: 1.6% | E7: ±0.8 | F7: 708 | G7: ±460 | H7: 1.5% | I7: ±0.9 | J7: 677 | K7: ±562 | L7: 1.6% | M7: ±1.4 | N7: 8,321 | O7: ±2,128 | P7: 2.0% | Q7: ±0.5 | R7: 2,695 | S7: ±871 | T7: 1.1% | U7: ±0.4 | V7: 5,626 | W7: ±1,851 | X7: 3.2% | Y7: ±1.1 | Z7: 8,135 | AA7: ±1,951 | AB7: 3.2% | AC7: ±0.8 | AD7: 2,245 | AE7: ±1,100 | AF7: 2.0% | AG7: ±1.0 | AH7: 5,890 | AI7: ±1,713 | AJ7: 4.2% | AK7: ±1.2 | AL7: 11,354 | AM7: ±2,116 | AN7: 1.6% | AO7: ±0.3 | AP7: 4,037 | AQ7: ±1,059 | AR7: 0.9% | AS7: ±0.2 | AT7: 7,317 | AU7: ±1,674 | AV7: 2.7% | AW7: ±0.6
A8: $10,000 to $14,999 | B8: 2,499 | C8: ±1,040 | D8: 2.8% | E8: ±1.2 | F8: 698 | G8: ±398 | H8: 1.5% | I8: ±0.8 | J8: 1,801 | K8: ±925 | L8: 4.4% | M8: ±2.3 | N8: 11,420 | O8: ±2,211 | P8: 2.8% | Q8: ±0.5 | R8: 5,264 | S8: ±1,246 | T8: 2.2% | U8: ±0.5 | V8: 6,156 | W8: ±1,701 | X8: 3.5% | Y8: ±1.0 | Z8: 13,299 | AA8: ±2,789 | AB8: 5.3% | AC8: ±1.1 | AD8: 3,167 | AE8: ±1,052 | AF8: 2.8% | AG8: ±0.9 | AH8: 10,132 | AI8: ±2,588 | AJ8: 7.3% | AK8: ±1.8 | AL8: 19,076 | AM8: ±2,688 | AN8: 2.7% | AO8: ±0.4 | AP8: 5,937 | AQ8: ±1,021 | AR8: 1.3% | AS8: ±0.2 | AT8: 13,139 | AU8: ±2,448 | AV8: 4.9% | AW8: ±0.9
A9: $15,000 to $19,999 | B9: 3,356 | C9: ±1,267 | D9: 3.8% | E9: ±1.4 | F9: 1,296 | G9: ±724 | H9: 2.7% | I9: ±1.5 | J9: 2,060 | K9: ±976 | L9: 5.0% | M9: ±2.3 | N9: 12,089 | O9: ±2,959 | P9: 2.9% | Q9: ±0.7 | R9: 5,100 | S9: ±1,684 | T9: 2.1% | U9: ±0.7 | V9: 6,989 | W9: ±2,156 | X9: 4.0% | Y9: ±1.2 | Z9: 10,184 | AA9: ±2,255 | AB9: 4.1% | AC9: ±0.9 | AD9: 3,159 | AE9: ±1,169 | AF9: 2.8% | AG9: ±1.1 | AH9: 7,025 | AI9: ±2,002 | AJ9: 5.1% | AK9: ±1.4 | AL9: 15,132 | AM9: ±2,667 | AN9: 2.1% | AO9: ±0.4 | AP9: 4,770 | AQ9: ±1,190 | AR9: 1.1% | AS9: ±0.3 | AT9: 10,362 | AU9: ±2,332 | AV9: 3.9% | AW9: ±0.8
A10: $20,000 to $24,999 | B10: 3,740 | C10: ±1,498 | D10: 4.2% | E10: ±1.7 | F10: 1,186 | G10: ±747 | H10: 2.5% | I10: ±1.6 | J10: 2,554 | K10: ±1,277 | L10: 6.2% | M10: ±3.1 | N10: 12,407 | O10: ±2,292 | P10: 3.0% | Q10: ±0.6 | R10: 4,379 | S10: ±1,185 | T10: 1.8% | U10: ±0.5 | V10: 8,028 | W10: ±2,028 | X10: 4.6% | Y10: ±1.1 | Z10: 14,833 | AA10: ±2,555 | AB10: 5.9% | AC10: ±1.0 | AD10: 4,704 | AE10: ±1,331 | AF10: 4.2% | AG10: ±1.2 | AH10: 10,129 | AI10: ±2,237 | AJ10: 7.3% | AK10: ±1.6 | AL10: 23,053 | AM10: ±2,749 | AN10: 3.2% | AO10: ±0.4 | AP10: 8,821 | AQ10: ±1,283 | AR10: 2.0% | AS10: ±0.3 | AT10: 14,232 | AU10: ±2,453 | AV10: 5.3% | AW10: ±0.9
A11: $25,000 to $34,999 | B11: 7,154 | C11: ±2,362 | D11: 8.1% | E11: ±2.6 | F11: 2,116 | G11: ±1,015 | H11: 4.5% | I11: ±2.1 | J11: 5,038 | K11: ±2,111 | L11: 12.2% | M11: ±4.9 | N11: 29,961 | O11: ±4,109 | P11: 7.2% | Q11: ±1.0 | R11: 11,875 | S11: ±2,001 | T11: 4.9% | U11: ±0.8 | V11: 18,086 | W11: ±3,716 | X11: 10.4% | Y11: ±2.1 | Z11: 19,796 | AA11: ±2,510 | AB11: 7.9% | AC11: ±1.0 | AD11: 6,651 | AE11: ±1,388 | AF11: 6.0% | AG11: ±1.2 | AH11: 13,145 | AI11: ±2,299 | AJ11: 9.5% | AK11: ±1.7 | AL11: 43,474 | AM11: ±4,288 | AN11: 6.1% | AO11: ±0.6 | AP11: 19,080 | AQ11: ±2,595 | AR11: 4.2% | AS11: ±0.6 | AT11: 24,394 | AU11: ±3,389 | AV11: 9.1% | AW11: ±1.3
A12: $35,000 to $49,999 | B12: 11,856 | C12: ±2,294 | D12: 13.4% | E12: ±2.6 | F12: 4,258 | G12: ±1,100 | H12: 9.0% | I12: ±2.2 | J12: 7,598 | K12: ±2,293 | L12: 18.4% | M12: ±5.2 | N12: 43,598 | O12: ±4,638 | P12: 10.5% | Q12: ±1.1 | R12: 18,001 | S12: ±2,372 | T12: 7.5% | U12: ±1.0 | V12: 25,597 | W12: ±3,947 | X12: 14.8% | Y12: ±2.2 | Z12: 34,536 | AA12: ±3,855 | AB12: 13.8% | AC12: ±1.5 | AD12: 12,436 | AE12: ±2,045 | AF12: 11.1% | AG12: ±1.8 | AH12: 22,100 | AI12: ±3,574 | AJ12: 15.9% | AK12: ±2.4 | AL12: 68,418 | AM12: ±4,890 | AN12: 9.5% | AO12: ±0.7 | AP12: 31,939 | AQ12: ±3,034 | AR12: 7.1% | AS12: ±0.6 | AT12: 36,479 | AU12: ±4,391 | AV12: 13.7% | AW12: ±1.6
A13: $50,000 to $74,999 | B13: 14,697 | C13: ±2,469 | D13: 16.6% | E13: ±2.7 | F13: 5,838 | G13: ±1,152 | H13: 12.3% | I13: ±2.4 | J13: 8,859 | K13: ±2,107 | L13: 21.4% | M13: ±4.9 | N13: 78,589 | O13: ±5,324 | P13: 19.0% | Q13: ±1.3 | R13: 40,871 | S13: ±3,412 | T13: 17.0% | U13: ±1.3 | V13: 37,718 | W13: ±4,464 | X13: 21.8% | Y13: ±2.5 | Z13: 44,673 | AA13: ±4,184 | AB13: 17.8% | AC13: ±1.6 | AD13: 19,767 | AE13: ±3,066 | AF13: 17.7% | AG13: ±2.6 | AH13: 24,906 | AI13: ±3,197 | AJ13: 17.9% | AK13: ±2.2 | AL13: 125,889 | AM13: ±6,290 | AN13: 17.5% | AO13: ±0.9 | AP13: 68,526 | AQ13: ±4,820 | AR13: 15.2% | AS13: ±1.0 | AT13: 57,363 | AU13: ±4,748 | AV13: 21.5% | AW13: ±1.6
A14: $75,000 to $99,999 | B14: 11,082 | C14: ±2,128 | D14: 12.5% | E14: ±2.3 | F14: 6,770 | G14: ±1,619 | H14: 14.3% | I14: ±3.2 | J14: 4,312 | K14: ±1,475 | L14: 10.4% | M14: ±3.5 | N14: 58,346 | O14: ±4,889 | P14: 14.1% | Q14: ±1.2 | R14: 32,490 | S14: ±3,695 | T14: 13.5% | U14: ±1.5 | V14: 25,856 | W14: ±4,197 | X14: 14.9% | Y14: ±2.3 | Z14: 31,172 | AA14: ±3,509 | AB14: 12.4% | AC14: ±1.4 | AD14: 14,666 | AE14: ±1,984 | AF14: 13.1% | AG14: ±1.7 | AH14: 16,506 | AI14: ±2,950 | AJ14: 11.9% | AK14: ±2.1 | AL14: 96,645 | AM14: ±4,961 | AN14: 13.5% | AO14: ±0.7 | AP14: 60,435 | AQ14: ±3,697 | AR14: 13.4% | AS14: ±0.8 | AT14: 36,210 | AU14: ±3,994 | AV14: 13.6% | AW14: ±1.4
A15: $100,000 to $149,999 | B15: 14,200 | C15: ±2,313 | D15: 16.0% | E15: ±2.6 | F15: 9,669 | G15: ±1,773 | H15: 20.4% | I15: ±3.5 | J15: 4,531 | K15: ±1,650 | L15: 10.9% | M15: ±3.9 | N15: 72,919 | O15: ±5,488 | P15: 17.6% | Q15: ±1.3 | R15: 55,515 | S15: ±4,560 | T15: 23.1% | U15: ±1.8 | V15: 17,404 | W15: ±3,065 | X15: 10.0% | Y15: ±1.7 | Z15: 30,426 | AA15: ±3,079 | AB15: 12.1% | AC15: ±1.2 | AD15: 17,086 | AE15: ±2,421 | AF15: 15.3% | AG15: ±2.1 | AH15: 13,340 | AI15: ±2,781 | AJ15: 9.6% | AK15: ±2.0 | AL15: 137,639 | AM15: ±5,284 | AN15: 19.2% | AO15: ±0.7 | AP15: 102,211 | AQ15: ±5,212 | AR15: 22.6% | AS15: ±1.0 | AT15: 35,428 | AU15: ±3,519 | AV15: 13.3% | AW15: ±1.3
A16: $150,000 or more | B16: 14,420 | C16: ±1,766 | D16: 16.3% | E16: ±2.0 | F16: 13,334 | G16: ±1,717 | H16: 28.2% | I16: ±3.5 | J16: 1,086 | K16: ±538 | L16: 2.6% | M16: ±1.3 | N16: 69,115 | O16: ±4,987 | P16: 16.7% | Q16: ±1.2 | R16: 57,351 | S16: ±4,756 | T16: 23.9% | U16: ±1.9 | V16: 11,764 | W16: ±2,777 | X16: 6.8% | Y16: ±1.6 | Z16: 25,864 | AA16: ±2,273 | AB16: 10.3% | AC16: ±0.9 | AD16: 21,510 | AE16: ±1,920 | AF16: 19.3% | AG16: ±1.7 | AH16: 4,354 | AI16: ±1,678 | AJ16: 3.1% | AK16: ±1.2 | AL16: 156,632 | AM16: ±5,841 | AN16: 21.8% | AO16: ±0.8 | AP16: 137,509 | AQ16: ±5,327 | AR16: 30.5% | AS16: ±1.1 | AT16: 19,123 | AU16: ±2,685 | AV16: 7.2% | AW16: ±1.0
A17: Median household income (dollars) | B17: 66,553 | C17: ±3,400 | D17: 66,553 | E17: ±3,400 | F17: 97,719 | G17: ±8,248 | H17: 97,719 | I17: ±8,248 | J17: 45,393 | K17: ±7,009 | L17: 45,393 | M17: ±7,009 | N17: 72,389 | O17: ±2,436 | P17: 72,389 | Q17: ±2,436 | R17: 92,720 | S17: ±4,096 | T17: 92,720 | U17: ±4,096 | V17: 53,641 | W17: ±3,880 | X17: 53,641 | Y17: ±3,880 | Z17: 52,679 | AA17: ±2,423 | AB17: 52,679 | AC17: ±2,423 | AD17: 71,480 | AE17: ±4,247 | AF17: 71,480 | AG17: ±4,247 | AH17: 41,982 | AI17: ±2,201 | AJ17: 41,982 | AK17: ±2,201 | AL17: 82,402 | AM17: ±1,660 | AN17: 82,402 | AO17: ±1,660 | AP17: 105,603 | AQ17: ±2,201 | AR17: 105,603 | AS17: ±2,201 | AT17: 54,460 | AU17: ±1,782 | AV17: 54,460 | AW17: ±1,782
A18: MONTHLY HOUSING COSTS
A19: Less than $300 | B19: 3,340 | C19: ±1,148 | D19: 3.8% | E19: ±1.3 | F19: 2,104 | G19: ±831 | H19: 4.4% | I19: ±1.7 | J19: 1,236 | K19: ±829 | L19: 3.0% | M19: ±2.0 | N19: 17,039 | O19: ±2,177 | P19: 4.1% | Q19: ±0.5 | R19: 13,520 | S19: ±1,827 | T19: 5.6% | U19: ±0.7 | V19: 3,519 | W19: ±1,116 | X19: 2.0% | Y19: ±0.7 | Z19: 7,960 | AA19: ±1,547 | AB19: 3.2% | AC19: ±0.6 | AD19: 5,681 | AE19: ±1,091 | AF19: 5.1% | AG19: ±1.0 | AH19: 2,279 | AI19: ±1,174 | AJ19: 1.6% | AK19: ±0.8 | AL19: 17,603 | AM19: ±2,256 | AN19: 2.5% | AO19: ±0.3 | AP19: 11,672 | AQ19: ±2,000 | AR19: 2.6% | AS19: ±0.4 | AT19: 5,931 | AU19: ±1,300 | AV19: 2.2% | AW19: ±0.5
A20: $300 to $499 | B20: 5,894 | C20: ±1,081 | D20: 6.6% | E20: ±1.2 | F20: 5,319 | G20: ±1,012 | H20: 11.2% | I20: ±2.2 | J20: 575 | K20: ±374 | L20: 1.4% | M20: ±0.9 | N20: 23,590 | O20: ±2,399 | P20: 5.7% | Q20: ±0.6 | R20: 19,397 | S20: ±2,052 | T20: 8.1% | U20: ±0.9 | V20: 4,193 | W20: ±1,333 | X20: 2.4% | Y20: ±0.8 | Z20: 18,968 | AA20: ±2,584 | AB20: 7.6% | AC20: ±1.0 | AD20: 15,963 | AE20: ±2,407 | AF20: 14.3% | AG20: ±2.1 | AH20: 3,005 | AI20: ±994 | AJ20: 2.2% | AK20: ±0.7 | AL20: 26,933 | AM20: ±2,630 | AN20: 3.8% | AO20: ±0.4 | AP20: 21,385 | AQ20: ±2,235 | AR20: 4.7% | AS20: ±0.5 | AT20: 5,548 | AU20: ±1,197 | AV20: 2.1% | AW20: ±0.4
A21: $500 to $799 | B21: 12,352 | C21: ±1,940 | D21: 13.9% | E21: ±2.0 | F21: 7,858 | G21: ±1,675 | H21: 16.6% | I21: ±3.1 | J21: 4,494 | K21: ±1,396 | L21: 10.9% | M21: ±3.2 | N21: 37,701 | O21: ±3,599 | P21: 9.1% | Q21: ±0.9 | R21: 30,049 | S21: ±3,196 | T21: 12.5% | U21: ±1.3 | V21: 7,652 | W21: ±2,232 | X21: 4.4% | Y21: ±1.3 | Z21: 31,830 | AA21: ±3,378 | AB21: 12.7% | AC21: ±1.3 | AD21: 19,435 | AE21: ±1,952 | AF21: 17.4% | AG21: ±1.8 | AH21: 12,395 | AI21: ±2,363 | AJ21: 8.9% | AK21: ±1.7 | AL21: 65,137 | AM21: ±4,526 | AN21: 9.1% | AO21: ±0.6 | AP21: 54,583 | AQ21: ±3,535 | AR21: 12.1% | AS21: ±0.7 | AT21: 10,554 | AU21: ±2,364 | AV21: 4.0% | AW21: ±0.9
A22: $800 to $999 | B22: 11,943 | C22: ±2,343 | D22: 13.5% | E22: ±2.5 | F22: 4,427 | G22: ±955 | H22: 9.4% | I22: ±2.0 | J22: 7,516 | K22: ±2,172 | L22: 18.2% | M22: ±4.9 | N22: 27,004 | O22: ±3,682 | P22: 6.5% | Q22: ±0.9 | R22: 17,681 | S22: ±2,828 | T22: 7.4% | U22: ±1.2 | V22: 9,323 | W22: ±2,231 | X22: 5.4% | Y22: ±1.3 | Z22: 28,950 | AA22: ±3,444 | AB22: 11.5% | AC22: ±1.4 | AD22: 11,710 | AE22: ±1,760 | AF22: 10.5% | AG22: ±1.6 | AH22: 17,240 | AI22: ±2,896 | AJ22: 12.4% | AK22: ±2.0 | AL22: 46,229 | AM22: ±3,441 | AN22: 6.4% | AO22: ±0.5 | AP22: 30,420 | AQ22: ±2,807 | AR22: 6.7% | AS22: ±0.6 | AT22: 15,809 | AU22: ±2,163 | AV22: 5.9% | AW22: ±0.8
A23: $1,000 to $1,499 | B23: 29,066 | C23: ±2,811 | D23: 32.8% | E23: ±3.0 | F23: 10,103 | G23: ±1,754 | H23: 21.3% | I23: ±3.2 | J23: 18,963 | K23: ±2,711 | L23: 45.8% | M23: ±5.5 | N23: 95,788 | O23: ±5,998 | P23: 23.2% | Q23: ±1.4 | R23: 44,181 | S23: ±3,948 | T23: 18.4% | U23: ±1.5 | V23: 51,607 | W23: ±5,272 | X23: 29.8% | Y23: ±3.0 | Z23: 84,972 | AA23: ±5,261 | AB23: 33.9% | AC23: ±1.9 | AD23: 24,168 | AE23: ±3,095 | AF23: 21.6% | AG23: ±2.6 | AH23: 60,804 | AI23: ±4,408 | AJ23: 43.7% | AK23: ±2.7 | AL23: 162,074 | AM23: ±7,481 | AN23: 22.6% | AO23: ±1.0 | AP23: 80,068 | AQ23: ±4,366 | AR23: 17.7% | AS23: ±0.9 | AT23: 82,006 | AU23: ±5,337 | AV23: 30.8% | AW23: ±1.8
A24: $1,500 to $1,999 | B24: 12,251 | C24: ±2,302 | D24: 13.8% | E24: ±2.5 | F24: 6,440 | G24: ±1,556 | H24: 13.6% | I24: ±3.2 | J24: 5,811 | K24: ±1,667 | L24: 14.0% | M24: ±3.8 | N24: 101,097 | O24: ±7,228 | P24: 24.4% | Q24: ±1.7 | R24: 41,618 | S24: ±3,856 | T24: 17.3% | U24: ±1.5 | V24: 59,479 | W24: ±5,807 | X24: 34.3% | Y24: ±2.9 | Z24: 40,825 | AA24: ±3,778 | AB24: 16.3% | AC24: ±1.5 | AD24: 13,355 | AE24: ±2,074 | AF24: 12.0% | AG24: ±1.8 | AH24: 27,470 | AI24: ±3,436 | AJ24: 19.7% | AK24: ±2.5 | AL24: 169,415 | AM24: ±7,141 | AN24: 23.6% | AO24: ±1.0 | AP24: 86,256 | AQ24: ±5,393 | AR24: 19.1% | AS24: ±1.1 | AT24: 83,159 | AU24: ±5,255 | AV24: 31.2% | AW24: ±1.6
A25: $2,000 to $2,499 | B25: 4,795 | C25: ±1,319 | D25: 5.4% | E25: ±1.5 | F25: 3,922 | G25: ±1,061 | H25: 8.3% | I25: ±2.1 | J25: 873 | K25: ±668 | L25: 2.1% | M25: ±1.6 | N25: 56,222 | O25: ±5,912 | P25: 13.6% | Q25: ±1.4 | R25: 31,719 | S25: ±4,189 | T25: 13.2% | U25: ±1.7 | V25: 24,503 | W25: ±4,152 | X25: 14.1% | Y25: ±2.2 | Z25: 14,190 | AA25: ±2,310 | AB25: 5.7% | AC25: ±0.9 | AD25: 8,364 | AE25: ±1,694 | AF25: 7.5% | AG25: ±1.5 | AH25: 5,826 | AI25: ±1,812 | AJ25: 4.2% | AK25: ±1.3 | AL25: 110,371 | AM25: ±6,409 | AN25: 15.4% | AO25: ±0.9 | AP25: 71,765 | AQ25: ±4,917 | AR25: 15.9% | AS25: ±1.0 | AT25: 38,606 | AU25: ±3,732 | AV25: 14.5% | AW25: ±1.4
A26: $2,500 to $2,999 | B26: 3,538 | C26: ±1,364 | D26: 4.0% | E26: ±1.6 | F26: 3,357 | G26: ±1,345 | H26: 7.1% | I26: ±2.9 | J26: 181 | K26: ±142 | L26: 0.4% | M26: ±0.3 | N26: 23,948 | O26: ±3,898 | P26: 5.8% | Q26: ±0.9 | R26: 17,640 | S26: ±3,107 | T26: 7.3% | U26: ±1.3 | V26: 6,308 | W26: ±1,837 | X26: 3.6% | Y26: ±1.0 | Z26: 7,136 | AA26: ±2,022 | AB26: 2.8% | AC26: ±0.8 | AD26: 4,394 | AE26: ±1,226 | AF26: 3.9% | AG26: ±1.1 | AH26: 2,742 | AI26: ±1,454 | AJ26: 2.0% | AK26: ±1.0 | AL26: 48,865 | AM26: ±3,794 | AN26: 6.8% | AO26: ±0.5 | AP26: 39,220 | AQ26: ±3,418 | AR26: 8.7% | AS26: ±0.7 | AT26: 9,645 | AU26: ±1,635 | AV26: 3.6% | AW26: ±0.6
A27: $3,000 or more | B27: 4,609 | C27: ±1,109 | D27: 5.2% | E27: ±1.3 | F27: 3,810 | G27: ±974 | H27: 8.0% | I27: ±2.0 | J27: 799 | K27: ±532 | L27: 1.9% | M27: ±1.3 | N27: 26,545 | O27: ±3,447 | P27: 6.4% | Q27: ±0.8 | R27: 24,404 | S27: ±3,279 | T27: 10.2% | U27: ±1.3 | V27: 2,141 | W27: ±1,230 | X27: 1.2% | Y27: ±0.7 | Z27: 10,565 | AA27: ±1,924 | AB27: 4.2% | AC27: ±0.8 | AD27: 8,667 | AE27: ±1,678 | AF27: 7.8% | AG27: ±1.5 | AH27: 1,898 | AI27: ±929 | AJ27: 1.4% | AK27: ±0.7 | AL27: 63,057 | AM27: ±3,740 | AN27: 8.8% | AO27: ±0.5 | AP27: 55,918 | AQ27: ±3,299 | AR27: 12.4% | AS27: ±0.7 | AT27: 7,139 | AU27: ±1,563 | AV27: 2.7% | AW27: ±0.6
A28: No cash rent | B28: 950 | C28: ±568 | D28: 1.1% | E28: ±0.6 | F28: (X) | G28: (X) | H28: (X) | I28: (X) | J28: 950 | K28: ±568 | L28: 2.3% | M28: ±1.4 | N28: 4,686 | O28: ±1,384 | P28: 1.1% | Q28: ±0.3 | R28: (X) | S28: (X) | T28: (X) | U28: (X) | V28: 4,686 | W28: ±1,384 | X28: 2.7% | Y28: ±0.8 | Z28: 5,434 | AA28: ±1,664 | AB28: 2.2% | AC28: ±0.7 | AD28: (X) | AE28: (X) | AF28: (X) | AG28: (X) | AH28: 5,434 | AI28: ±1,664 | AJ28: 3.9% | AK28: ±1.2 | AL28: 8,227 | AM28: ±1,875 | AN28: 1.1% | AO28: ±0.3 | AP28: (X) | AQ28: (X) | AR28: (X) | AS28: (X) | AT28: 8,227 | AU28: ±1,875 | AV28: 3.1% | AW28: ±0.7
A29: Median (dollars) | B29: 1,152 | C29: ±34 | D29: 1,152 | E29: ±34 | F29: 1,189 | G29: ±89 | H29: 1,189 | I29: ±89 | J29: 1,136 | K29: ±42 | L29: 1,136 | M29: ±42 | N29: 1,514 | O29: ±26 | P29: 1,514 | Q29: ±26 | R29: 1,450 | S29: ±47 | T29: 1,450 | U29: ±47 | V29: 1,568 | W29: ±41 | X29: 1,568 | Y29: ±41 | Z29: 1,201 | AA29: ±28 | AB29: 1,201 | AC29: ±28 | AD29: 1,058 | AE29: ±53 | AF29: 1,058 | AG29: ±53 | AH29: 1,263 | AI29: ±31 | AJ29: 1,263 | AK29: ±31 | AL29: 1,602 | AM29: ±21 | AN29: 1,602 | AO29: ±21 | AP29: 1,663 | AQ29: ±35 | AR29: 1,663 | AS29: ±35 | AT29: 1,556 | AU29: ±28 | AV29: 1,556 | AW29: ±28
A30: MONTHLY HOUSING COSTS AS A PERCENTAGE OF HOUSEHOLD INCOME IN THE PAST 12 MONTHS
A31: Less than $20,000 | B31: 8,433 | C31: ±2,152 | D31: 9.5% | E31: ±2.3 | F31: 3,481 | G31: ±1,278 | H31: 7.4% | I31: ±2.5 | J31: 4,952 | K31: ±1,445 | L31: 12.0% | M31: ±3.5 | N31: 42,117 | O31: ±4,057 | P31: 10.2% | Q31: ±1.0 | R31: 17,140 | S31: ±2,470 | T31: 7.1% | U31: ±1.0 | V31: 24,977 | W31: ±3,520 | X31: 14.4% | Y31: ±2.0 | Z31: 40,856 | AA31: ±3,863 | AB31: 16.3% | AC31: ±1.5 | AD31: 13,012 | AE31: ±2,220 | AF31: 11.6% | AG31: ±1.9 | AH31: 27,844 | AI31: ±3,387 | AJ31: 20.0% | AK31: ±2.4 | AL31: 56,461 | AM31: ±3,683 | AN31: 7.9% | AO31: ±0.5 | AP31: 19,575 | AQ31: ±2,159 | AR31: 4.3% | AS31: ±0.5 | AT31: 36,886 | AU31: ±3,448 | AV31: 13.8% | AW31: ±1.2
A32: Less than 20 percent | B32: 101 | C32: ±143 | D32: 0.1% | E32: ±0.2 | F32: 76 | G32: ±136 | H32: 0.2% | I32: ±0.3 | J32: 25 | K32: ±42 | L32: 0.1% | M32: ±0.1 | N32: 1,271 | O32: ±498 | P32: 0.3% | Q32: ±0.1 | R32: 1,077 | S32: ±473 | T32: 0.4% | U32: ±0.2 | V32: 194 | W32: ±260 | X32: 0.1% | Y32: ±0.2 | Z32: 594 | AA32: ±380 | AB32: 0.2% | AC32: ±0.2 | AD32: 435 | AE32: ±287 | AF32: 0.4% | AG32: ±0.3 | AH32: 159 | AI32: ±266 | AJ32: 0.1% | AK32: ±0.2 | AL32: 1,091 | AM32: ±492 | AN32: 0.2% | AO32: ±0.1 | AP32: 363 | AQ32: ±221 | AR32: 0.1% | AS32: ±0.1 | AT32: 728 | AU32: ±469 | AV32: 0.3% | AW32: ±0.2
A33: 20 to 29 percent | B33: 708 | C33: ±555 | D33: 0.8% | E33: ±0.6 | F33: 77 | G33: ±94 | H33: 0.2% | I33: ±0.2 | J33: 631 | K33: ±527 | L33: 1.5% | M33: ±1.3 | N33: 2,910 | O33: ±1,119 | P33: 0.7% | Q33: ±0.3 | R33: 647 | S33: ±363 | T33: 0.3% | U33: ±0.2 | V33: 2,263 | W33: ±1,041 | X33: 1.3% | Y33: ±0.6 | Z33: 1,930 | AA33: ±951 | AB33: 0.8% | AC33: ±0.4 | AD33: 510 | AE33: ±323 | AF33: 0.5% | AG33: ±0.3 | AH33: 1,420 | AI33: ±874 | AJ33: 1.0% | AK33: ±0.6 | AL33: 4,030 | AM33: ±1,244 | AN33: 0.6% | AO33: ±0.2 | AP33: 928 | AQ33: ±394 | AR33: 0.2% | AS33: ±0.1 | AT33: 3,102 | AU33: ±1,103 | AV33: 1.2% | AW33: ±0.4
A34: 30 percent or more | B34: 7,624 | C34: ±2,127 | D34: 8.6% | E34: ±2.3 | F34: 3,328 | G34: ±1,264 | H34: 7.0% | I34: ±2.5 | J34: 4,296 | K34: ±1,470 | L34: 10.4% | M34: ±3.7 | N34: 37,936 | O34: ±4,051 | P34: 9.2% | Q34: ±1.0 | R34: 15,416 | S34: ±2,434 | T34: 6.4% | U34: ±1.0 | V34: 22,520 | W34: ±3,625 | X34: 13.0% | Y34: ±2.0 | Z34: 38,332 | AA34: ±3,625 | AB34: 15.3% | AC34: ±1.4 | AD34: 12,067 | AE34: ±2,122 | AF34: 10.8% | AG34: ±1.8 | AH34: 26,265 | AI34: ±3,064 | AJ34: 18.9% | AK34: ±2.2 | AL34: 51,340 | AM34: ±3,707 | AN34: 7.2% | AO34: ±0.5 | AP34: 18,284 | AQ34: ±2,040 | AR34: 4.1% | AS34: ±0.5 | AT34: 33,056 | AU34: ±3,408 | AV34: 12.4% | AW34: ±1.2
A35: $20,000 to $34,999 | B35: 10,665 | C35: ±2,586 | D35: 12.0% | E35: ±2.9 | F35: 3,302 | G35: ±1,052 | H35: 7.0% | I35: ±2.2 | J35: 7,363 | K35: ±2,239 | L35: 17.8% | M35: ±5.2 | N35: 41,046 | O35: ±4,383 | P35: 9.9% | Q35: ±1.0 | R35: 16,254 | S35: ±1,982 | T35: 6.8% | U35: ±0.8 | V35: 24,792 | W35: ±3,932 | X35: 14.3% | Y35: ±2.1 | Z35: 34,172 | AA35: ±3,248 | AB35: 13.6% | AC35: ±1.3 | AD35: 11,355 | AE35: ±1,953 | AF35: 10.2% | AG35: ±1.7 | AH35: 22,817 | AI35: ±2,875 | AJ35: 16.4% | AK35: ±2.1 | AL35: 65,033 | AM35: ±5,272 | AN35: 9.1% | AO35: ±0.7 | AP35: 27,901 | AQ35: ±2,782 | AR35: 6.2% | AS35: ±0.6 | AT35: 37,132 | AU35: ±3,943 | AV35: 13.9% | AW35: ±1.5
A36: Less than 20 percent | B36: 995 | C36: ±543 | D36: 1.1% | E36: ±0.6 | F36: 995 | G36: ±543 | H36: 2.1% | I36: ±1.2 | J36: 0 | K36: ±213 | L36: 0.0% | M36: ±0.5 | N36: 4,622 | O36: ±1,076 | P36: 1.1% | Q36: ±0.3 | R36: 4,006 | S36: ±989 | T36: 1.7% | U36: ±0.4 | V36: 616 | W36: ±405 | X36: 0.4% | Y36: ±0.2 | Z36: 3,363 | AA36: ±1,047 | AB36: 1.3% | AC36: ±0.4 | AD36: 2,381 | AE36: ±891 | AF36: 2.1% | AG36: ±0.8 | AH36: 982 | AI36: ±693 | AJ36: 0.7% | AK36: ±0.5 | AL36: 6,321 | AM36: ±1,734 | AN36: 0.9% | AO36: ±0.2 | AP36: 4,834 | AQ36: ±1,413 | AR36: 1.1% | AS36: ±0.3 | AT36: 1,487 | AU36: ±863 | AV36: 0.6% | AW36: ±0.3
A37: 20 to 29 percent | B37: 930 | C37: ±781 | D37: 1.0% | E37: ±0.9 | F37: 770 | G37: ±780 | H37: 1.6% | I37: ±1.6 | J37: 160 | K37: ±162 | L37: 0.4% | M37: ±0.4 | N37: 3,481 | O37: ±1,006 | P37: 0.8% | Q37: ±0.2 | R37: 2,641 | S37: ±780 | T37: 1.1% | U37: ±0.3 | V37: 840 | W37: ±605 | X37: 0.5% | Y37: ±0.3 | Z37: 4,577 | AA37: ±1,381 | AB37: 1.8% | AC37: ±0.6 | AD37: 3,029 | AE37: ±1,141 | AF37: 2.7% | AG37: ±1.0 | AH37: 1,548 | AI37: ±838 | AJ37: 1.1% | AK37: ±0.6 | AL37: 7,472 | AM37: ±1,715 | AN37: 1.0% | AO37: ±0.2 | AP37: 5,562 | AQ37: ±1,439 | AR37: 1.2% | AS37: ±0.3 | AT37: 1,910 | AU37: ±862 | AV37: 0.7% | AW37: ±0.3
A38: 30 percent or more | B38: 8,740 | C38: ±2,447 | D38: 9.8% | E38: ±2.7 | F38: 1,537 | G38: ±907 | H38: 3.2% | I38: ±1.9 | J38: 7,203 | K38: ±2,242 | L38: 17.4% | M38: ±5.2 | N38: 32,943 | O38: ±4,093 | P38: 8.0% | Q38: ±0.9 | R38: 9,607 | S38: ±1,822 | T38: 4.0% | U38: ±0.8 | V38: 23,336 | W38: ±3,657 | X38: 13.5% | Y38: ±2.0 | Z38: 26,232 | AA38: ±3,092 | AB38: 10.5% | AC38: ±1.3 | AD38: 5,945 | AE38: ±1,333 | AF38: 5.3% | AG38: ±1.2 | AH38: 20,287 | AI38: ±2,744 | AJ38: 14.6% | AK38: ±2.0 | AL38: 51,240 | AM38: ±4,488 | AN38: 7.1% | AO38: ±0.6 | AP38: 17,505 | AQ38: ±1,963 | AR38: 3.9% | AS38: ±0.4 | AT38: 33,735 | AU38: ±3,880 | AV38: 12.7% | AW38: ±1.5
A39: $35,000 to $49,999 | B39: 11,768 | C39: ±2,304 | D39: 13.3% | E39: ±2.6 | F39: 4,258 | G39: ±1,100 | H39: 9.0% | I39: ±2.2 | J39: 7,510 | K39: ±2,304 | L39: 18.1% | M39: ±5.3 | N39: 43,267 | O39: ±4,602 | P39: 10.5% | Q39: ±1.1 | R39: 18,001 | S39: ±2,372 | T39: 7.5% | U39: ±1.0 | V39: 25,266 | W39: ±3,924 | X39: 14.6% | Y39: ±2.2 | Z39: 34,150 | AA39: ±3,808 | AB39: 13.6% | AC39: ±1.5 | AD39: 12,436 | AE39: ±2,045 | AF39: 11.1% | AG39: ±1.8 | AH39: 21,714 | AI39: ±3,539 | AJ39: 15.6% | AK39: ±2.4 | AL39: 67,412 | AM39: ±4,847 | AN39: 9.4% | AO39: ±0.7 | AP39: 31,939 | AQ39: ±3,034 | AR39: 7.1% | AS39: ±0.6 | AT39: 35,473 | AU39: ±4,373 | AV39: 13.3% | AW39: ±1.6
A40: Less than 20 percent | B40: 2,037 | C40: ±704 | D40: 2.3% | E40: ±0.8 | F40: 1,662 | G40: ±658 | H40: 3.5% | I40: ±1.4 | J40: 375 | K40: ±326 | L40: 0.9% | M40: ±0.8 | N40: 8,354 | O40: ±1,420 | P40: 2.0% | Q40: ±0.3 | R40: 7,011 | S40: ±1,237 | T40: 2.9% | U40: ±0.5 | V40: 1,343 | W40: ±973 | X40: 0.8% | Y40: ±0.6 | Z40: 5,418 | AA40: ±1,381 | AB40: 2.2% | AC40: ±0.6 | AD40: 5,105 | AE40: ±1,344 | AF40: 4.6% | AG40: ±1.2 | AH40: 313 | AI40: ±260 | AJ40: 0.2% | AK40: ±0.2 | AL40: 12,302 | AM40: ±1,937 | AN40: 1.7% | AO40: ±0.3 | AP40: 10,793 | AQ40: ±1,724 | AR40: 2.4% | AS40: ±0.4 | AT40: 1,509 | AU40: ±740 | AV40: 0.6% | AW40: ±0.3
A41: 20 to 29 percent | B41: 4,057 | C41: ±1,330 | D41: 4.6% | E41: ±1.5 | F41: 1,400 | G41: ±635 | H41: 3.0% | I41: ±1.3 | J41: 2,657 | K41: ±1,225 | L41: 6.4% | M41: ±2.9 | N41: 4,286 | O41: ±1,117 | P41: 1.0% | Q41: ±0.3 | R41: 2,092 | S41: ±741 | T41: 0.9% | U41: ±0.3 | V41: 2,194 | W41: ±948 | X41: 1.3% | Y41: ±0.5 | Z41: 7,711 | AA41: ±2,055 | AB41: 3.1% | AC41: ±0.8 | AD41: 2,602 | AE41: ±899 | AF41: 2.3% | AG41: ±0.8 | AH41: 5,109 | AI41: ±1,853 | AJ41: 3.7% | AK41: ±1.3 | AL41: 7,996 | AM41: ±1,501 | AN41: 1.1% | AO41: ±0.2 | AP41: 4,403 | AQ41: ±902 | AR41: 1.0% | AS41: ±0.2 | AT41: 3,593 | AU41: ±1,126 | AV41: 1.3% | AW41: ±0.4
A42: 30 percent or more | B42: 5,674 | C42: ±1,850 | D42: 6.4% | E42: ±2.1 | F42: 1,196 | G42: ±646 | H42: 2.5% | I42: ±1.3 | J42: 4,478 | K42: ±1,826 | L42: 10.8% | M42: ±4.3 | N42: 30,627 | O42: ±4,347 | P42: 7.4% | Q42: ±1.0 | R42: 8,898 | S42: ±1,931 | T42: 3.7% | U42: ±0.8 | V42: 21,729 | W42: ±3,962 | X42: 12.5% | Y42: ±2.3 | Z42: 21,021 | AA42: ±3,325 | AB42: 8.4% | AC42: ±1.3 | AD42: 4,729 | AE42: ±1,305 | AF42: 4.2% | AG42: ±1.2 | AH42: 16,292 | AI42: ±3,132 | AJ42: 11.7% | AK42: ±2.2 | AL42: 47,114 | AM42: ±3,985 | AN42: 6.6% | AO42: ±0.6 | AP42: 16,743 | AQ42: ±2,076 | AR42: 3.7% | AS42: ±0.5 | AT42: 30,371 | AU42: ±3,778 | AV42: 11.4% | AW42: ±1.4
... A52: No cash rent | B52: 950 | C52: ±568 | D52: 1.1% | E52: ±0.6 | F52: (X) | G52: (X) | H52: (X) | I52: (X) | J52: 950 | K52: ±568 | L52: 2.3% | M52: ±1.4 | N52: 4,686 | O52: ±1,384 | P52: 1.1% | Q52: ±0.3 | R52: (X) | S52: (X) | T52: (X) | U52: (X) | V52: 4,686 | W52: ±1,384 | X52: 2.7% | Y52: ±0.8 | Z52: 5,434 | AA52: ±1,664 | AB52: 2.2% | AC52: ±0.7 | AD52: (X) | AE52: (X) | AF52: (X) | AG52: (X) | AH52: 5,434 | AI52: ±1,664 | AJ52: 3.9% | AK52: ±1.2 | AL52: 8,227 | AM52: ±1,875 | AN52: 1.1% | AO52: ±0.3 | AP52: (X) | AQ52: (X) | AR52: (X) | AS52: (X) | AT52: 8,227 | AU52: ±1,875 | AV52: 3.1% | AW52: ±0.7

Sheet Income (2020)
B1: Little Rock city, Arkansas | N1: Jacksonville city, Florida | Z1: Memphis city, Tennessee | AL1: Virginia Beach-Norfolk-Newport News, VA-NC Metro Area
B2: Occupied housing units | D2: Percent occupied housing units | F2: Owner-occupied housing units | H2: Percent owner-occupied housing units | J2: Renter-occupied housing units | L2: Percent renter-occupied housing units | N2: Occupied housing units | P2: Percent occupied housing units | R2: Owner-occupied housing units | T2: Percent owner-occupied housing units | V2: Renter-occupied housing units | X2: Percent renter-occupied housing units | Z2: Occupied housing units | AB2: Percent occupied housing units | AD2: Owner-occupied housing units | AF2: Percent owner-occupied housing units | AH2: Renter-occupied housing units | AJ2: Percent renter-occupied housing units | AL2: Occupied housing units | AN2: Percent occupied housing units | AP2: Owner-occupied housing units | AR2: Percent owner-occupied housing units | AT2: Renter-occupied housing units | AV2: Percent renter-occupied housing units
A3: Label | B3: Estimate | C3: Margin of Error | D3: Estimate | E3: Margin of Error | F3: Estimate | G3: Margin of Error | H3: Estimate | I3: Margin of Error | J3: Estimate | K3: Margin of Error | L3: Estimate | M3: Margin of Error | N3: Estimate | O3: Margin of Error | P3: Estimate | Q3: Margin of Error | R3: Estimate | S3: Margin of Error | T3: Estimate | U3: Margin of Error | V3: Estimate | W3: Margin of Error | X3: Estimate | Y3: Margin of Error | Z3: Estimate | AA3: Margin of Error | AB3: Estimate | AC3: Margin of Error | AD3: Estimate | AE3: Margin of Error | AF3: Estimate | AG3: Margin of Error | AH3: Estimate | AI3: Margin of Error | AJ3: Estimate | AK3: Margin of Error | AL3: Estimate | AM3: Margin of Error | AN3: Estimate | AO3: Margin of Error | AP3: Estimate | AQ3: Margin of Error | AR3: Estimate | AS3: Margin of Error | AT3: Estimate | AU3: Margin of Error | AV3: Estimate | AW3: Margin of Error
A4: Occupied housing units | B4: 83,525 | C4: ±1,328 | D4: 83,525 | E4: ±1,328 | F4: 45,625 | G4: ±1,464 | H4: 45,625 | I4: ±1,464 | J4: 37,900 | K4: ±1,341 | L4: 37,900 | M4: ±1,341 | N4: 348,809 | O4: ±2,342 | P4: 348,809 | Q4: ±2,342 | R4: 196,649 | S4: ±2,556 | T4: 196,649 | U4: ±2,556 | V4: 152,160 | W4: ±2,801 | X4: 152,160 | Y4: ±2,801 | Z4: 255,756 | AA4: ±2,087 | AB4: 255,756 | AC4: ±2,087 | AD4: 118,235 | AE4: ±2,383 | AF4: 118,235 | AG4: ±2,383 | AH4: 137,521 | AI4: ±2,353 | AJ4: 137,521 | AK4: ±2,353 | AL4: 672,053 | AM4: ±2,310 | AN4: 672,053 | AO4: ±2,310 | AP4: 418,960 | AQ4: ±3,643 | AR4: 418,960 | AS4: ±3,643 | AT4: 253,093 | AU4: ±3,104 | AV4: 253,093 | AW4: ±3,104
A5: HOUSEHOLD INCOME IN THE PAST 12 MONTHS (IN 2020 INFLATION-ADJUSTED DOLLARS)
A6: Less than $5,000 | B6: 4,065 | C6: ±613 | D6: 4.9% | E6: ±0.7 | F6: 1,187 | G6: ±272 | H6: 2.6% | I6: ±0.6 | J6: 2,878 | K6: ±565 | L6: 7.6% | M6: ±1.5 | N6: 14,463 | O6: ±1,175 | P6: 4.1% | Q6: ±0.3 | R6: 5,082 | S6: ±743 | T6: 2.6% | U6: ±0.4 | V6: 9,381 | W6: ±1,109 | X6: 6.2% | Y6: ±0.7 | Z6: 16,117 | AA6: ±1,123 | AB6: 6.3% | AC6: ±0.4 | AD6: 3,359 | AE6: ±514 | AF6: 2.8% | AG6: ±0.4 | AH6: 12,758 | AI6: ±901 | AJ6: 9.3% | AK6: ±0.6 | AL6: 19,340 | AM6: ±1,315 | AN6: 2.9% | AO6: ±0.2 | AP6: 5,702 | AQ6: ±586 | AR6: 1.4% | AS6: ±0.1 | AT6: 13,638 | AU6: ±961 | AV6: 5.4% | AW6: ±0.4
A7: $5,000 to $9,999 | B7: 2,654 | C7: ±358 | D7: 3.2% | E7: ±0.4 | F7: 600 | G7: ±176 | H7: 1.3% | I7: ±0.4 | J7: 2,054 | K7: ±357 | L7: 5.4% | M7: ±0.9 | N7: 9,964 | O7: ±867 | P7: 2.9% | Q7: ±0.2 | R7: 3,198 | S7: ±650 | T7: 1.6% | U7: ±0.3 | V7: 6,766 | W7: ±783 | X7: 4.4% | Y7: ±0.5 | Z7: 11,396 | AA7: ±725 | AB7: 4.5% | AC7: ±0.3 | AD7: 2,401 | AE7: ±429 | AF7: 2.0% | AG7: ±0.4 | AH7: 8,995 | AI7: ±627 | AJ7: 6.5% | AK7: ±0.5 | AL7: 15,483 | AM7: ±996 | AN7: 2.3% | AO7: ±0.1 | AP7: 3,790 | AQ7: ±425 | AR7: 0.9% | AS7: ±0.1 | AT7: 11,693 | AU7: ±952 | AV7: 4.6% | AW7: ±0.4
A8: $10,000 to $14,999 | B8: 3,213 | C8: ±493 | D8: 3.8% | E8: ±0.6 | F8: 953 | G8: ±199 | H8: 2.1% | I8: ±0.4 | J8: 2,260 | K8: ±431 | L8: 6.0% | M8: ±1.1 | N8: 14,106 | O8: ±1,090 | P8: 4.0% | Q8: ±0.3 | R8: 6,073 | S8: ±686 | T8: 3.1% | U8: ±0.3 | V8: 8,033 | W8: ±729 | X8: 5.3% | Y8: ±0.5 | Z8: 18,866 | AA8: ±1,076 | AB8: 7.4% | AC8: ±0.4 | AD8: 5,729 | AE8: ±780 | AF8: 4.8% | AG8: ±0.6 | AH8: 13,137 | AI8: ±889 | AJ8: 9.6% | AK8: ±0.6 | AL8: 20,210 | AM8: ±996 | AN8: 3.0% | AO8: ±0.1 | AP8: 6,854 | AQ8: ±609 | AR8: 1.6% | AS8: ±0.1 | AT8: 13,356 | AU8: ±805 | AV8: 5.3% | AW8: ±0.3
A9: $15,000 to $19,999 | B9: 3,797 | C9: ±644 | D9: 4.5% | E9: ±0.8 | F9: 1,552 | G9: ±365 | H9: 3.4% | I9: ±0.8 | J9: 2,245 | K9: ±462 | L9: 5.9% | M9: ±1.3 | N9: 14,397 | O9: ±1,123 | P9: 4.1% | Q9: ±0.3 | R9: 5,283 | S9: ±553 | T9: 2.7% | U9: ±0.3 | V9: 9,114 | W9: ±993 | X9: 6.0% | Y9: ±0.7 | Z9: 16,543 | AA9: ±1,128 | AB9: 6.5% | AC9: ±0.4 | AD9: 5,202 | AE9: ±589 | AF9: 4.4% | AG9: ±0.5 | AH9: 11,341 | AI9: ±907 | AJ9: 8.2% | AK9: ±0.7 | AL9: 22,662 | AM9: ±1,189 | AN9: 3.4% | AO9: ±0.2 | AP9: 9,566 | AQ9: ±696 | AR9: 2.3% | AS9: ±0.2 | AT9: 13,096 | AU9: ±909 | AV9: 5.2% | AW9: ±0.4
A10: $20,000 to $24,999 | B10: 5,379 | C10: ±935 | D10: 6.4% | E10: ±1.1 | F10: 2,109 | G10: ±537 | H10: 4.6% | I10: ±1.1 | J10: 3,270 | K10: ±722 | L10: 8.6% | M10: ±1.9 | N10: 17,689 | O10: ±1,269 | P10: 5.1% | Q10: ±0.4 | R10: 6,905 | S10: ±710 | T10: 3.5% | U10: ±0.4 | V10: 10,784 | W10: ±1,000 | X10: 7.1% | Y10: ±0.7 | Z10: 16,018 | AA10: ±1,056 | AB10: 6.3% | AC10: ±0.4 | AD10: 5,376 | AE10: ±610 | AF10: 4.5% | AG10: ±0.5 | AH10: 10,642 | AI10: ±952 | AJ10: 7.7% | AK10: ±0.7 | AL10: 26,588 | AM10: ±1,462 | AN10: 4.0% | AO10: ±0.2 | AP10: 10,890 | AQ10: ±908 | AR10: 2.6% | AS10: ±0.2 | AT10: 15,698 | AU10: ±1,050 | AV10: 6.2% | AW10: ±0.4
A11: $25,000 to $34,999 | B11: 8,879 | C11: ±794 | D11: 10.6% | E11: ±0.9 | F11: 3,143 | G11: ±455 | H11: 6.9% | I11: ±0.9 | J11: 5,736 | K11: ±715 | L11: 15.1% | M11: ±1.8 | N11: 34,575 | O11: ±1,693 | P11: 9.9% | Q11: ±0.5 | R11: 14,661 | S11: ±1,206 | T11: 7.5% | U11: ±0.6 | V11: 19,914 | W11: ±1,357 | X11: 13.1% | Y11: ±0.8 | Z11: 30,963 | AA11: ±1,573 | AB11: 12.1% | AC11: ±0.6 | AD11: 10,761 | AE11: ±667 | AF11: 9.1% | AG11: ±0.6 | AH11: 20,202 | AI11: ±1,555 | AJ11: 14.7% | AK11: ±1.1 | AL11: 52,791 | AM11: ±1,755 | AN11: 7.9% | AO11: ±0.3 | AP11: 23,868 | AQ11: ±1,120 | AR11: 5.7% | AS11: ±0.3 | AT11: 28,923 | AU11: ±1,438 | AV11: 11.4% | AW11: ±0.5
A12: $35,000 to $49,999 | B12: 11,342 | C12: ±754 | D12: 13.6% | E12: ±0.9 | F12: 5,007 | G12: ±621 | H12: 11.0% | I12: ±1.3 | J12: 6,335 | K12: ±678 | L12: 16.7% | M12: ±1.7 | N12: 49,994 | O12: ±2,146 | P12: 14.3% | Q12: ±0.6 | R12: 23,030 | S12: ±1,341 | T12: 11.7% | U12: ±0.7 | V12: 26,964 | W12: ±1,712 | X12: 17.7% | Y12: ±1.0 | Z12: 37,262 | AA12: ±1,787 | AB12: 14.6% | AC12: ±0.7 | AD12: 15,874 | AE12: ±1,193 | AF12: 13.4% | AG12: ±1.0 | AH12: 21,388 | AI12: ±1,416 | AJ12: 15.6% | AK12: ±1.0 | AL12: 82,212 | AM12: ±2,018 | AN12: 12.2% | AO12: ±0.3 | AP12: 39,443 | AQ12: ±1,554 | AR12: 9.4% | AS12: ±0.4 | AT12: 42,769 | AU12: ±1,825 | AV12: 16.9% | AW12: ±0.7
A13: $50,000 to $74,999 | B13: 14,467 | C13: ±1,054 | D13: 17.3% | E13: ±1.2 | F13: 8,098 | G13: ±842 | H13: 17.7% | I13: ±1.7 | J13: 6,369 | K13: ±723 | L13: 16.8% | M13: ±1.7 | N13: 67,772 | O13: ±2,013 | P13: 19.4% | Q13: ±0.6 | R13: 37,611 | S13: ±1,600 | T13: 19.1% | U13: ±0.8 | V13: 30,161 | W13: ±1,599 | X13: 19.8% | Y13: ±1.1 | Z13: 42,529 | AA13: ±1,849 | AB13: 16.6% | AC13: ±0.7 | AD13: 21,387 | AE13: ±1,286 | AF13: 18.1% | AG13: ±1.0 | AH13: 21,142 | AI13: ±1,440 | AJ13: 15.4% | AK13: ±1.0 | AL13: 126,118 | AM13: ±2,546 | AN13: 18.8% | AO13: ±0.4 | AP13: 74,259 | AQ13: ±2,008 | AR13: 17.7% | AS13: ±0.4 | AT13: 51,859 | AU13: ±1,683 | AV13: 20.5% | AW13: ±0.6
A14: $75,000 to $99,999 | B14: 9,110 | C14: ±747 | D14: 10.9% | E14: ±0.9 | F14: 5,378 | G14: ±608 | H14: 11.8% | I14: ±1.3 | J14: 3,732 | K14: ±543 | L14: 9.8% | M14: ±1.4 | N14: 45,650 | O14: ±2,362 | P14: 13.1% | Q14: ±0.7 | R14: 29,799 | S14: ±1,739 | T14: 15.2% | U14: ±0.8 | V14: 15,851 | W14: ±1,263 | X14: 10.4% | Y14: ±0.8 | Z14: 24,075 | AA14: ±1,345 | AB14: 9.4% | AC14: ±0.5 | AD14: 15,227 | AE14: ±960 | AF14: 12.9% | AG14: ±0.8 | AH14: 8,848 | AI14: ±963 | AJ14: 6.4% | AK14: ±0.7 | AL14: 94,729 | AM14: ±2,175 | AN14: 14.1% | AO14: ±0.3 | AP14: 67,414 | AQ14: ±1,983 | AR14: 16.1% | AS14: ±0.4 | AT14: 27,315 | AU14: ±1,207 | AV14: 10.8% | AW14: ±0.5
A15: $100,000 to $149,999 | B15: 9,660 | C15: ±762 | D15: 11.6% | E15: ±0.9 | F15: 7,444 | G15: ±644 | H15: 16.3% | I15: ±1.4 | J15: 2,216 | K15: ±492 | L15: 5.8% | M15: ±1.3 | N15: 46,315 | O15: ±1,891 | P15: 13.3% | Q15: ±0.5 | R15: 35,457 | S15: ±1,738 | T15: 18.0% | U15: ±0.9 | V15: 10,858 | W15: ±921 | X15: 7.1% | Y15: ±0.6 | Z15: 23,296 | AA15: ±1,341 | AB15: 9.1% | AC15: ±0.5 | AD15: 16,833 | AE15: ±1,137 | AF15: 14.2% | AG15: ±0.9 | AH15: 6,463 | AI15: ±758 | AJ15: 4.7% | AK15: ±0.5 | AL15: 118,835 | AM15: ±2,588 | AN15: 17.7% | AO15: ±0.4 | AP15: 94,467 | AQ15: ±2,611 | AR15: 22.5% | AS15: ±0.6 | AT15: 24,368 | AU15: ±1,318 | AV15: 9.6% | AW15: ±0.5
A16: $150,000 or more | B16: 10,959 | C16: ±662 | D16: 13.1% | E16: ±0.8 | F16: 10,154 | G16: ±654 | H16: 22.3% | I16: ±1.4 | J16: 805 | K16: ±232 | L16: 2.1% | M16: ±0.6 | N16: 33,884 | O16: ±1,492 | P16: 9.7% | Q16: ±0.4 | R16: 29,550 | S16: ±1,526 | T16: 15.0% | U16: ±0.8 | V16: 4,334 | W16: ±616 | X16: 2.8% | Y16: ±0.4 | Z16: 18,691 | AA16: ±1,076 | AB16: 7.3% | AC16: ±0.4 | AD16: 16,086 | AE16: ±977 | AF16: 13.6% | AG16: ±0.8 | AH16: 2,605 | AI16: ±387 | AJ16: 1.9% | AK16: ±0.3 | AL16: 93,085 | AM16: ±2,285 | AN16: 13.9% | AO16: ±0.3 | AP16: 82,707 | AQ16: ±2,222 | AR16: 19.7% | AS16: ±0.5 | AT16: 10,378 | AU16: ±808 | AV16: 4.1% | AW16: ±0.3
A17: Median household income (dollars) | B17: 53,620 | C17: ±1,752 | D17: 53,620 | E17: ±1,752 | F17: 75,948 | G17: ±4,356 | H17: 75,948 | I17: ±4,356 | J17: 36,166 | K17: ±2,083 | L17: 36,166 | M17: ±2,083 | N17: 55,531 | O17: ±989 | P17: 55,531 | Q17: ±989 | R17: 72,322 | S17: ±1,341 | T17: 72,322 | U17: ±1,341 | V17: 41,010 | W17: ±979 | X17: 41,010 | Y17: ±979 | Z17: 41,864 | AA17: ±733 | AB17: 41,864 | AC17: ±733 | AD17: 60,976 | AE17: ±1,836 | AF17: 60,976 | AG17: ±1,836 | AH17: 30,973 | AI17: ±662 | AJ17: 30,973 | AK17: ±662 | AL17: 68,454 | AM17: ±753 | AN17: 68,454 | AO17: ±753 | AP17: 87,425 | AQ17: ±945 | AR17: 87,425 | AS17: ±945 | AT17: 45,242 | AU17: ±633 | AV17: 45,242 | AW17: ±633
A18: MONTHLY HOUSING COSTS
A19: Less than $300 | B19: 4,065 | C19: ±514 | D19: 4.9% | E19: ±0.6 | F19: 2,752 | G19: ±443 | H19: 6.0% | I19: ±1.0 | J19: 1,313 | K19: ±281 | L19: 3.5% | M19: ±0.7 | N19: 20,080 | O19: ±1,257 | P19: 5.8% | Q19: ±0.4 | R19: 15,094 | S19: ±1,081 | T19: 7.7% | U19: ±0.6 | V19: 4,986 | W19: ±535 | X19: 3.3% | Y19: ±0.4 | Z19: 14,220 | AA19: ±1,010 | AB19: 5.6% | AC19: ±0.4 | AD19: 10,167 | AE19: ±877 | AF19: 8.6% | AG19: ±0.7 | AH19: 4,053 | AI19: ±467 | AJ19: 2.9% | AK19: ±0.3 | AL19: 21,165 | AM19: ±1,050 | AN19: 3.1% | AO19: ±0.2 | AP19: 12,739 | AQ19: ±824 | AR19: 3.0% | AS19: ±0.2 | AT19: 8,426 | AU19: ±666 | AV19: 3.3% | AW19: ±0.3
A20: $300 to $499 | B20: 8,007 | C20: ±875 | D20: 9.6% | E20: ±1.0 | F20: 6,326 | G20: ±800 | H20: 13.9% | I20: ±1.6 | J20: 1,681 | K20: ±342 | L20: 4.4% | M20: ±0.9 | N20: 29,408 | O20: ±1,496 | P20: 8.4% | Q20: ±0.4 | R20: 25,579 | S20: ±1,428 | T20: 13.0% | U20: ±0.7 | V20: 3,829 | W20: ±553 | X20: 2.5% | Y20: ±0.4 | Z20: 24,402 | AA20: ±1,222 | AB20: 9.5% | AC20: ±0.5 | AD20: 18,870 | AE20: ±1,027 | AF20: 16.0% | AG20: ±0.8 | AH20: 5,532 | AI20: ±665 | AJ20: 4.0% | AK20: ±0.5 | AL20: 45,496 | AM20: ±1,534 | AN20: 6.8% | AO20: ±0.2 | AP20: 37,730 | AQ20: ±1,473 | AR20: 9.0% | AS20: ±0.4 | AT20: 7,766 | AU20: ±691 | AV20: 3.1% | AW20: ±0.3
A21: $500 to $799 | B21: 18,931 | C21: ±1,313 | D21: 22.7% | E21: ±1.4 | F21: 8,329 | G21: ±840 | H21: 18.3% | I21: ±1.7 | J21: 10,602 | K21: ±1,013 | L21: 28.0% | M21: ±2.5 | N21: 51,757 | O21: ±1,887 | P21: 14.8% | Q21: ±0.5 | R21: 31,535 | S21: ±1,324 | T21: 16.0% | U21: ±0.6 | V21: 20,222 | W21: ±1,452 | X21: 13.3% | Y21: ±0.9 | Z21: 55,792 | AA21: ±1,810 | AB21: 21.8% | AC21: ±0.7 | AD21: 22,288 | AE21: ±857 | AF21: 18.9% | AG21: ±0.7 | AH21: 33,504 | AI21: ±1,601 | AJ21: 24.4% | AK21: ±1.1 | AL21: 78,527 | AM21: ±2,148 | AN21: 11.7% | AO21: ±0.3 | AP21: 56,995 | AQ21: ±1,891 | AR21: 13.6% | AS21: ±0.4 | AT21: 21,532 | AU21: ±1,238 | AV21: 8.5% | AW21: ±0.5
A22: $800 to $999 | B22: 15,005 | C22: ±1,219 | D22: 18.0% | E22: ±1.4 | F22: 5,390 | G22: ±672 | H22: 11.8% | I22: ±1.4 | J22: 9,615 | K22: ±1,002 | L22: 25.4% | M22: ±2.4 | N22: 49,392 | O22: ±2,051 | P22: 14.2% | Q22: ±0.6 | R22: 19,009 | S22: ±1,167 | T22: 9.7% | U22: ±0.6 | V22: 30,383 | W22: ±1,663 | X22: 20.0% | Y22: ±1.0 | Z22: 52,522 | AA22: ±2,006 | AB22: 20.5% | AC22: ±0.8 | AD22: 14,762 | AE22: ±1,032 | AF22: 12.5% | AG22: ±0.9 | AH22: 37,760 | AI22: ±1,689 | AJ22: 27.5% | AK22: ±1.2 | AL22: 68,984 | AM22: ±2,226 | AN22: 10.3% | AO22: ±0.3 | AP22: 28,791 | AQ22: ±1,334 | AR22: 6.9% | AS22: ±0.3 | AT22: 40,193 | AU22: ±1,587 | AV22: 15.9% | AW22: ±0.6
A23: $1,000 to $1,499 | B23: 21,019 | C23: ±1,107 | D23: 25.2% | E23: ±1.3 | F23: 10,095 | G23: ±709 | H23: 22.1% | I23: ±1.5 | J23: 10,924 | K23: ±1,018 | L23: 28.8% | M23: ±2.3 | N23: 111,751 | O23: ±2,721 | P23: 32.0% | Q23: ±0.7 | R23: 48,092 | S23: ±2,059 | T23: 24.5% | U23: ±1.0 | V23: 63,659 | W23: ±2,036 | X23: 41.8% | Y23: ±1.2 | Z23: 70,538 | AA23: ±2,303 | AB23: 27.6% | AC23: ±0.9 | AD23: 28,433 | AE23: ±1,510 | AF23: 24.0% | AG23: ±1.1 | AH23: 42,105 | AI23: ±2,137 | AJ23: 30.6% | AK23: ±1.4 | AL23: 190,566 | AM23: ±2,783 | AN23: 28.4% | AO23: ±0.4 | AP23: 87,966 | AQ23: ±2,220 | AR23: 21.0% | AS23: ±0.5 | AT23: 102,600 | AU23: ±2,040 | AV23: 40.5% | AW23: ±0.8
A24: $1,500 to $1,999 | B24: 7,076 | C24: ±555 | D24: 8.5% | E24: ±0.7 | F24: 5,375 | G24: ±513 | H24: 11.8% | I24: ±1.1 | J24: 1,701 | K24: ±376 | L24: 4.5% | M24: ±1.0 | N24: 50,213 | O24: ±2,151 | P24: 14.4% | Q24: ±0.6 | R24: 31,473 | S24: ±1,722 | T24: 16.0% | U24: ±0.8 | V24: 18,740 | W24: ±1,618 | X24: 12.3% | Y24: ±1.0 | Z24: 19,607 | AA24: ±974 | AB24: 7.7% | AC24: ±0.4 | AD24: 11,821 | AE24: ±802 | AF24: 10.0% | AG24: ±0.6 | AH24: 7,786 | AI24: ±768 | AJ24: 5.7% | AK24: ±0.6 | AL24: 135,134 | AM24: ±2,324 | AN24: 20.1% | AO24: ±0.3 | AP24: 89,252 | AQ24: ±2,254 | AR24: 21.3% | AS24: ±0.5 | AT24: 45,882 | AU24: ±1,839 | AV24: 18.1% | AW24: ±0.6
A25: $2,000 to $2,499 | B25: 3,545 | C25: ±506 | D25: 4.2% | E25: ±0.6 | F25: 3,143 | G25: ±469 | H25: 6.9% | I25: ±1.0 | J25: 402 | K25: ±135 | L25: 1.1% | M25: ±0.4 | N25: 16,968 | O25: ±1,303 | P25: 4.9% | Q25: ±0.4 | R25: 13,190 | S25: ±1,061 | T25: 6.7% | U25: ±0.5 | V25: 3,778 | W25: ±599 | X25: 2.5% | Y25: ±0.4 | Z25: 6,667 | AA25: ±790 | AB25: 2.6% | AC25: ±0.3 | AD25: 5,493 | AE25: ±834 | AF25: 4.6% | AG25: ±0.7 | AH25: 1,174 | AI25: ±338 | AJ25: 0.9% | AK25: ±0.2 | AL25: 65,500 | AM25: ±2,004 | AN25: 9.7% | AO25: ±0.3 | AP25: 53,411 | AQ25: ±1,752 | AR25: 12.7% | AS25: ±0.4 | AT25: 12,089 | AU25: ±855 | AV25: 4.8% | AW25: ±0.3
A26: $2,500 to $2,999 | B26: 2,083 | C26: ±328 | D26: 2.5% | E26: ±0.4 | F26: 1,856 | G26: ±311 | H26: 4.1% | I26: ±0.7 | J26: 227 | K26: ±102 | L26: 0.6% | M26: ±0.3 | N26: 6,634 | O26: ±675 | P26: 1.9% | Q26: ±0.2 | R26: 6,181 | S26: ±681 | T26: 3.1% | U26: ±0.3 | V26: 453 | W26: ±191 | X26: 0.3% | Y26: ±0.1 | Z26: 2,711 | AA26: ±406 | AB26: 1.1% | AC26: ±0.2 | AD26: 2,449 | AE26: ±387 | AF26: 2.1% | AG26: ±0.3 | AH26: 262 | AI26: ±103 | AJ26: 0.2% | AK26: ±0.1 | AL26: 30,752 | AM26: ±1,363 | AN26: 4.6% | AO26: ±0.2 | AP26: 27,197 | AQ26: ±1,289 | AR26: 6.5% | AS26: ±0.3 | AT26: 3,555 | AU26: ±533 | AV26: 1.4% | AW26: ±0.2
A27: $3,000 or more | B27: 2,593 | C27: ±440 | D27: 3.1% | E27: ±0.5 | F27: 2,359 | G27: ±421 | H27: 5.2% | I27: ±0.9 | J27: 234 | K27: ±101 | L27: 0.6% | M27: ±0.3 | N27: 7,119 | O27: ±710 | P27: 2.0% | Q27: ±0.2 | R27: 6,496 | S27: ±666 | T27: 3.3% | U27: ±0.3 | V27: 623 | W27: ±210 | X27: 0.4% | Y27: ±0.1 | Z27: 4,221 | AA27: ±610 | AB27: 1.7% | AC27: ±0.2 | AD27: 3,952 | AE27: ±558 | AF27: 3.3% | AG27: ±0.5 | AH27: 269 | AI27: ±117 | AJ27: 0.2% | AK27: ±0.1 | AL27: 27,363 | AM27: ±1,067 | AN27: 4.1% | AO27: ±0.2 | AP27: 24,879 | AQ27: ±1,094 | AR27: 5.9% | AS27: ±0.3 | AT27: 2,484 | AU27: ±334 | AV27: 1.0% | AW27: ±0.1
A28: No cash rent | B28: 1,201 | C28: ±303 | D28: 1.4% | E28: ±0.4 | F28: (X) | G28: (X) | H28: (X) | I28: (X) | J28: 1,201 | K28: ±303 | L28: 3.2% | M28: ±0.8 | N28: 5,487 | O28: ±941 | P28: 1.6% | Q28: ±0.3 | R28: (X) | S28: (X) | T28: (X) | U28: (X) | V28: 5,487 | W28: ±941 | X28: 3.6% | Y28: ±0.6 | Z28: 5,076 | AA28: ±656 | AB28: 2.0% | AC28: ±0.3 | AD28: (X) | AE28: (X) | AF28: (X) | AG28: (X) | AH28: 5,076 | AI28: ±656 | AJ28: 3.7% | AK28: ±0.5 | AL28: 8,566 | AM28: ±623 | AN28: 1.3% | AO28: ±0.1 | AP28: (X) | AQ28: (X) | AR28: (X) | AS28: (X) | AT28: 8,566 | AU28: ±623 | AV28: 3.4% | AW28: ±0.2
A29: Median (dollars) | B29: 930 | C29: ±17 | D29: 930 | E29: ±17 | F29: 1,001 | G29: ±35 | H29: 1,001 | I29: ±35 | J29: 889 | K29: ±17 | L29: 889 | M29: ±17 | N29: 1,082 | O29: ±9 | P29: 1,082 | Q29: ±9 | R29: 1,071 | S29: ±20 | T29: 1,071 | U29: ±20 | V29: 1,089 | W29: ±10 | X29: 1,089 | Y29: ±10 | Z29: 913 | AA29: ±9 | AB29: 913 | AC29: ±9 | AD29: 909 | AE29: ±16 | AF29: 909 | AG29: ±16 | AH29: 915 | AI29: ±10 | AJ29: 915 | AK29: ±10 | AL29: 1,299 | AM29: ±8 | AN29: 1,299 | AO29: ±8 | AP29: 1,423 | AQ29: ±11 | AR29: 1,423 | AS29: ±11 | AT29: 1,187 | AU29: ±8 | AV29: 1,187 | AW29: ±8
A30: MONTHLY HOUSING COSTS AS A PERCENTAGE OF HOUSEHOLD INCOME IN THE PAST 12 MONTHS
A31: Less than $20,000 | B31: 11,208 | C31: ±855 | D31: 13.4% | E31: ±1.0 | F31: 3,767 | G31: ±476 | H31: 8.3% | I31: ±1.0 | J31: 7,441 | K31: ±666 | L31: 19.6% | M31: ±1.7 | N31: 44,235 | O31: ±1,969 | P31: 12.7% | Q31: ±0.6 | R31: 17,331 | S31: ±1,166 | T31: 8.8% | U31: ±0.6 | V31: 26,904 | W31: ±1,612 | X31: 17.7% | Y31: ±1.0 | Z31: 52,646 | AA31: ±1,645 | AB31: 20.6% | AC31: ±0.6 | AD31: 14,999 | AE31: ±1,184 | AF31: 12.7% | AG31: ±0.9 | AH31: 37,647 | AI31: ±1,354 | AJ31: 27.4% | AK31: ±1.0 | AL31: 67,434 | AM31: ±1,867 | AN31: 10.0% | AO31: ±0.3 | AP31: 23,565 | AQ31: ±1,076 | AR31: 5.6% | AS31: ±0.2 | AT31: 43,869 | AU31: ±1,524 | AV31: 17.3% | AW31: ±0.5
A32: Less than 20 percent | B32: 675 | C32: ±276 | D32: 0.8% | E32: ±0.3 | F32: 496 | G32: ±277 | H32: 1.1% | I32: ±0.6 | J32: 179 | K32: ±107 | L32: 0.5% | M32: ±0.3 | N32: 2,574 | O32: ±453 | P32: 0.7% | Q32: ±0.1 | R32: 1,580 | S32: ±335 | T32: 0.8% | U32: ±0.2 | V32: 994 | W32: ±275 | X32: 0.7% | Y32: ±0.2 | Z32: 1,764 | AA32: ±374 | AB32: 0.7% | AC32: ±0.1 | AD32: 1,386 | AE32: ±351 | AF32: 1.2% | AG32: ±0.3 | AH32: 378 | AI32: ±139 | AJ32: 0.3% | AK32: ±0.1 | AL32: 2,835 | AM32: ±394 | AN32: 0.4% | AO32: ±0.1 | AP32: 1,359 | AQ32: ±257 | AR32: 0.3% | AS32: ±0.1 | AT32: 1,476 | AU32: ±286 | AV32: 0.6% | AW32: ±0.1
A33: 20 to 29 percent | B33: 958 | C33: ±224 | D33: 1.1% | E33: ±0.3 | F33: 435 | G33: ±174 | H33: 1.0% | I33: ±0.4 | J33: 523 | K33: ±165 | L33: 1.4% | M33: ±0.4 | N33: 4,689 | O33: ±698 | P33: 1.3% | Q33: ±0.2 | R33: 2,559 | S33: ±525 | T33: 1.3% | U33: ±0.3 | V33: 2,130 | W33: ±461 | X33: 1.4% | Y33: ±0.3 | Z33: 4,170 | AA33: ±485 | AB33: 1.6% | AC33: ±0.2 | AD33: 2,005 | AE33: ±352 | AF33: 1.7% | AG33: ±0.3 | AH33: 2,165 | AI33: ±367 | AJ33: 1.6% | AK33: ±0.3 | AL33: 5,490 | AM33: ±583 | AN33: 0.8% | AO33: ±0.1 | AP33: 2,291 | AQ33: ±320 | AR33: 0.5% | AS33: ±0.1 | AT33: 3,199 | AU33: ±439 | AV33: 1.3% | AW33: ±0.2
A34: 30 percent or more | B34: 9,575 | C34: ±797 | D34: 11.5% | E34: ±0.9 | F34: 2,836 | G34: ±410 | H34: 6.2% | I34: ±0.9 | J34: 6,739 | K34: ±678 | L34: 17.8% | M34: ±1.8 | N34: 36,972 | O34: ±1,783 | P34: 10.6% | Q34: ±0.5 | R34: 13,192 | S34: ±990 | T34: 6.7% | U34: ±0.5 | V34: 23,780 | W34: ±1,524 | X34: 15.6% | Y34: ±1.0 | Z34: 46,712 | AA34: ±1,476 | AB34: 18.3% | AC34: ±0.6 | AD34: 11,608 | AE34: ±989 | AF34: 9.8% | AG34: ±0.8 | AH34: 35,104 | AI34: ±1,365 | AJ34: 25.5% | AK34: ±1.0 | AL34: 59,109 | AM34: ±1,922 | AN34: 8.8% | AO34: ±0.3 | AP34: 19,915 | AQ34: ±1,037 | AR34: 4.8% | AS34: ±0.2 | AT34: 39,194 | AU34: ±1,522 | AV34: 15.5% | AW34: ±0.5
A35: $20,000 to $34,999 | B35: 14,046 | C35: ±1,169 | D35: 16.8% | E35: ±1.3 | F35: 5,252 | G35: ±745 | H35: 11.5% | I35: ±1.5 | J35: 8,794 | K35: ±955 | L35: 23.2% | M35: ±2.4 | N35: 50,924 | O35: ±2,203 | P35: 14.6% | Q35: ±0.6 | R35: 21,566 | S35: ±1,463 | T35: 11.0% | U35: ±0.7 | V35: 29,358 | W35: ±1,790 | X35: 19.3% | Y35: ±1.1 | Z35: 45,924 | AA35: ±1,675 | AB35: 18.0% | AC35: ±0.6 | AD35: 16,137 | AE35: ±923 | AF35: 13.6% | AG35: ±0.8 | AH35: 29,787 | AI35: ±1,805 | AJ35: 21.7% | AK35: ±1.2 | AL35: 77,688 | AM35: ±2,144 | AN35: 11.6% | AO35: ±0.3 | AP35: 34,758 | AQ35: ±1,521 | AR35: 8.3% | AS35: ±0.4 | AT35: 42,930 | AU35: ±1,516 | AV35: 17.0% | AW35: ±0.6
A36: Less than 20 percent | B36: 1,444 | C36: ±285 | D36: 1.7% | E36: ±0.3 | F36: 1,117 | G36: ±234 | H36: 2.4% | I36: ±0.5 | J36: 327 | K36: ±158 | L36: 0.9% | M36: ±0.4 | N36: 7,070 | O36: ±720 | P36: 2.0% | Q36: ±0.2 | R36: 6,272 | S36: ±696 | T36: 3.2% | U36: ±0.4 | V36: 798 | W36: ±270 | X36: 0.5% | Y36: ±0.2 | Z36: 5,771 | AA36: ±597 | AB36: 2.3% | AC36: ±0.2 | AD36: 5,065 | AE36: ±562 | AF36: 4.3% | AG36: ±0.5 | AH36: 706 | AI36: ±251 | AJ36: 0.5% | AK36: ±0.2 | AL36: 8,574 | AM36: ±728 | AN36: 1.3% | AO36: ±0.1 | AP36: 6,961 | AQ36: ±632 | AR36: 1.7% | AS36: ±0.1 | AT36: 1,613 | AU36: ±361 | AV36: 0.6% | AW36: ±0.1
A37: 20 to 29 percent | B37: 2,928 | C37: ±655 | D37: 3.5% | E37: ±0.8 | F37: 1,506 | G37: ±541 | H37: 3.3% | I37: ±1.1 | J37: 1,422 | K37: ±400 | L37: 3.8% | M37: ±1.1 | N37: 7,225 | O37: ±756 | P37: 2.1% | Q37: ±0.2 | R37: 4,359 | S37: ±572 | T37: 2.2% | U37: ±0.3 | V37: 2,866 | W37: ±439 | X37: 1.9% | Y37: ±0.3 | Z37: 7,920 | AA37: ±836 | AB37: 3.1% | AC37: ±0.3 | AD37: 3,412 | AE37: ±479 | AF37: 2.9% | AG37: ±0.4 | AH37: 4,508 | AI37: ±701 | AJ37: 3.3% | AK37: ±0.5 | AL37: 10,496 | AM37: ±773 | AN37: 1.6% | AO37: ±0.1 | AP37: 6,889 | AQ37: ±589 | AR37: 1.6% | AS37: ±0.1 | AT37: 3,607 | AU37: ±530 | AV37: 1.4% | AW37: ±0.2
A38: 30 percent or more | B38: 9,674 | C38: ±1,031 | D38: 11.6% | E38: ±1.2 | F38: 2,629 | G38: ±472 | H38: 5.8% | I38: ±1.0 | J38: 7,045 | K38: ±961 | L38: 18.6% | M38: ±2.4 | N38: 36,629 | O38: ±2,006 | P38: 10.5% | Q38: ±0.6 | R38: 10,935 | S38: ±1,205 | T38: 5.6% | U38: ±0.6 | V38: 25,694 | W38: ±1,712 | X38: 16.9% | Y38: ±1.1 | Z38: 32,233 | AA38: ±1,604 | AB38: 12.6% | AC38: ±0.6 | AD38: 7,660 | AE38: ±728 | AF38: 6.5% | AG38: ±0.6 | AH38: 24,573 | AI38: ±1,596 | AJ38: 17.9% | AK38: ±1.1 | AL38: 58,618 | AM38: ±1,766 | AN38: 8.7% | AO38: ±0.3 | AP38: 20,908 | AQ38: ±1,190 | AR38: 5.0% | AS38: ±0.3 | AT38: 37,710 | AU38: ±1,340 | AV38: 14.9% | AW38: ±0.5
A39: $35,000 to $49,999 | B39: 11,290 | C39: ±754 | D39: 13.5% | E39: ±0.9 | F39: 5,007 | G39: ±621 | H39: 11.0% | I39: ±1.3 | J39: 6,283 | K39: ±681 | L39: 16.6% | M39: ±1.7 | N39: 48,998 | O39: ±1,978 | P39: 14.0% | Q39: ±0.6 | R39: 23,030 | S39: ±1,341 | T39: 11.7% | U39: ±0.7 | V39: 25,968 | W39: ±1,557 | X39: 17.1% | Y39: ±1.0 | Z39: 36,839 | AA39: ±1,769 | AB39: 14.4% | AC39: ±0.7 | AD39: 15,874 | AE39: ±1,193 | AF39: 13.4% | AG39: ±1.0 | AH39: 20,965 | AI39: ±1,403 | AJ39: 15.2% | AK39: ±0.9 | AL39: 80,695 | AM39: ±1,976 | AN39: 12.0% | AO39: ±0.3 | AP39: 39,443 | AQ39: ±1,554 | AR39: 9.4% | AS39: ±0.4 | AT39: 41,252 | AU39: ±1,746 | AV39: 16.3% | AW39: ±0.7
A40: Less than 20 percent | B40: 3,323 | C40: ±437 | D40: 4.0% | E40: ±0.5 | F40: 2,189 | G40: ±351 | H40: 4.8% | I40: ±0.8 | J40: 1,134 | K40: ±309 | L40: 3.0% | M40: ±0.8 | N40: 11,658 | O40: ±916 | P40: 3.3% | Q40: ±0.3 | R40: 10,080 | S40: ±821 | T40: 5.1% | U40: ±0.4 | V40: 1,578 | W40: ±353 | X40: 1.0% | Y40: ±0.2 | Z40: 9,298 | AA40: ±735 | AB40: 3.6% | AC40: ±0.3 | AD40: 7,231 | AE40: ±642 | AF40: 6.1% | AG40: ±0.5 | AH40: 2,067 | AI40: ±370 | AJ40: 1.5% | AK40: ±0.3 | AL40: 14,929 | AM40: ±838 | AN40: 2.2% | AO40: ±0.1 | AP40: 12,394 | AQ40: ±797 | AR40: 3.0% | AS40: ±0.2 | AT40: 2,535 | AU40: ±402 | AV40: 1.0% | AW40: ±0.2
A41: 20 to 29 percent | B41: 4,534 | C41: ±564 | D41: 5.4% | E41: ±0.7 | F41: 1,237 | G41: ±299 | H41: 2.7% | I41: ±0.6 | J41: 3,297 | K41: ±524 | L41: 8.7% | M41: ±1.3 | N41: 13,533 | O41: ±1,147 | P41: 3.9% | Q41: ±0.3 | R41: 4,807 | S41: ±502 | T41: 2.4% | U41: ±0.3 | V41: 8,726 | W41: ±890 | X41: 5.7% | Y41: ±0.6 | Z41: 15,587 | AA41: ±1,202 | AB41: 6.1% | AC41: ±0.5 | AD41: 4,524 | AE41: ±633 | AF41: 3.8% | AG41: ±0.5 | AH41: 11,063 | AI41: ±1,036 | AJ41: 8.0% | AK41: ±0.7 | AL41: 19,285 | AM41: ±1,158 | AN41: 2.9% | AO41: ±0.2 | AP41: 7,418 | AQ41: ±609 | AR41: 1.8% | AS41: ±0.1 | AT41: 11,867 | AU41: ±957 | AV41: 4.7% | AW41: ±0.4
A42: 30 percent or more | B42: 3,433 | C42: ±553 | D42: 4.1% | E42: ±0.7 | F42: 1,581 | G42: ±390 | H42: 3.5% | I42: ±0.8 | J42: 1,852 | K42: ±420 | L42: 4.9% | M42: ±1.1 | N42: 23,807 | O42: ±1,382 | P42: 6.8% | Q42: ±0.4 | R42: 8,143 | S42: ±879 | T42: 4.1% | U42: ±0.4 | V42: 15,664 | W42: ±1,205 | X42: 10.3% | Y42: ±0.8 | Z42: 11,954 | AA42: ±1,171 | AB42: 4.7% | AC42: ±0.5 | AD42: 4,119 | AE42: ±472 | AF42: 3.5% | AG42: ±0.4 | AH42: 7,835 | AI42: ±1,060 | AJ42: 5.7% | AK42: ±0.7 | AL42: 46,481 | AM42: ±1,655 | AN42: 6.9% | AO42: ±0.2 | AP42: 19,631 | AQ42: ±1,109 | AR42: 4.7% | AS42: ±0.3 | AT42: 26,850 | AU42: ±1,399 | AV42: 10.6% | AW42: ±0.5
... A52: No cash rent | B52: 1,201 | C52: ±303 | D52: 1.4% | E52: ±0.4 | F52: (X) | G52: (X) | H52: (X) | I52: (X) | J52: 1,201 | K52: ±303 | L52: 3.2% | M52: ±0.8 | N52: 5,487 | O52: ±941 | P52: 1.6% | Q52: ±0.3 | R52: (X) | S52: (X) | T52: (X) | U52: (X) | V52: 5,487 | W52: ±941 | X52: 3.6% | Y52: ±0.6 | Z52: 5,076 | AA52: ±656 | AB52: 2.0% | AC52: ±0.3 | AD52: (X) | AE52: (X) | AF52: (X) | AG52: (X) | AH52: 5,076 | AI52: ±656 | AJ52: 3.7% | AK52: ±0.5 | AL52: 8,566 | AM52: ±623 | AN52: 1.3% | AO52: ±0.1 | AP52: (X) | AQ52: (X) | AR52: (X) | AS52: (X) | AT52: 8,566 | AU52: ±623 | AV52: 3.4% | AW52: ±0.2

Sheet Population (2020)
A1: Label | B1: Little Rock city, Arkansas | C1: Jacksonville city, Florida | D1: Memphis city, Tennessee | E1: Virginia Beach-Norfolk-Newport News, VA-NC Metro Area
A2: Total: | B2: 202,591 | C2: 949,611 | D2: 633,104 | E2: 1,799,674
A3: Population of one race: | B3: 191,033 | C3: 863,393 | D3: 603,557 | E3: 1,653,281
A4: White alone | B4: 88,083 | C4: 475,813 | D4: 158,380 | E4: 971,907
A5: Black or African American alone | B5: 82,340 | C5: 290,279 | D5: 389,779 | E5: 544,740
A6: American Indian and Alaska Native alone | B6: 1,196 | C6: 3,578 | D6: 2,501 | E6: 8,043
A7: Asian alone | B7: 7,143 | C7: 48,617 | D7: 11,624 | E7: 73,979
A8: Native Hawaiian and Other Pacific Islander alone | B8: 78 | C8: 1,054 | D8: 198 | E8: 2,913
A9: Some Other Race alone | B9: 12,193 | C9: 44,052 | D9: 41,075 | E9: 51,699
A10: Population of two or more races: | B10: 11,558 | C10: 86,218 | D10: 29,547 | E10: 146,393
A11: Population of two races: | B11: 10,766 | C11: 80,303 | D11: 27,639 | E11: 132,543
A12: White; Black or African American | B12: 1,843 | C12: 12,814 | D12: 6,217 | E12: 29,210
... A72: White; Black or African American; American Indian and Alaska Native; Asian; Native Hawaiian and Other Pacific Islander; Some Other Race | B72: 0 | C72: 1 | D72: 2 | E72: 5

Sheet Population (2024)
B1: Little Rock city, Arkansas | F1: Jacksonville city, Florida | J1: Memphis city, Tennessee | N1: Virginia Beach-Chesapeake-Norfolk, VA-NC Metro Area
A2: Label | B2: Estimate | C2: Margin of Error | D2: Percent | E2: Percent Margin of Error | F2: Estimate | G2: Margin of Error | H2: Percent | I2: Percent Margin of Error | J2: Estimate | K2: Margin of Error | L2: Percent | M2: Percent Margin of Error | N2: Estimate | O2: Margin of Error | P2: Percent | Q2: Percent Margin of Error
A3: SEX AND AGE
A4: Total population | B4: 204,793 | C4: ±68 | D4: 204,793 | E4: (X) | F4: 1,009,831 | G4: ±22 | H4: 1,009,831 | I4: (X) | J4: 610,936 | K4: ±64 | L4: 610,936 | M4: (X) | N4: 1,796,689 | O4: ±4,440 | P4: 1,796,689 | Q4: (X)
A5: Male | B5: 98,539 | C5: ±3,136 | D5: 48.1% | E5: ±1.5 | F5: 489,191 | G5: ±1,479 | H5: 48.4% | I5: ±0.1 | J5: 288,142 | K5: ±4,448 | L5: 47.2% | M5: ±0.7 | N5: 884,794 | O5: ±4,682 | P5: 49.2% | Q5: ±0.2
A6: Female | B6: 106,254 | C6: ±3,143 | D6: 51.9% | E6: ±1.5 | F6: 520,640 | G6: ±1,479 | H6: 51.6% | I6: ±0.1 | J6: 322,794 | K6: ±4,440 | L6: 52.8% | M6: ±0.7 | N6: 911,895 | O6: ±4,662 | P6: 50.8% | Q6: ±0.2
A7: Sex ratio (males per 100 females) | B7: 92.7 | C7: ±5.7 | D7: (X) | E7: (X) | F7: 94.0 | G7: ±0.6 | H7: (X) | I7: (X) | J7: 89.3 | K7: ±2.6 | L7: (X) | M7: (X) | N7: 97.0 | O7: ±0.9 | P7: (X) | Q7: (X)
A8: Under 5 years | B8: 14,196 | C8: ±2,707 | D8: 6.9% | E8: ±1.3 | F8: 61,503 | G8: ±1,267 | H8: 6.1% | I8: ±0.1 | J8: 44,399 | K8: ±2,679 | L8: 7.3% | M8: ±0.4 | N8: 102,324 | O8: ±1,845 | P8: 5.7% | Q8: ±0.1
A9: 5 to 9 years | B9: 14,757 | C9: ±2,785 | D9: 7.2% | E9: ±1.4 | F9: 62,946 | G9: ±3,748 | H9: 6.2% | I9: ±0.4 | J9: 38,299 | K9: ±3,877 | L9: 6.3% | M9: ±0.6 | N9: 104,478 | O9: ±4,557 | P9: 5.8% | Q9: ±0.3
A10: 10 to 14 years | B10: 13,619 | C10: ±2,520 | D10: 6.7% | E10: ±1.2 | F10: 62,114 | G10: ±3,702 | H10: 6.2% | I10: ±0.4 | J10: 43,996 | K10: ±4,352 | L10: 7.2% | M10: ±0.7 | N10: 116,636 | O10: ±4,345 | P10: 6.5% | Q10: ±0.2
A11: 15 to 19 years | B11: 14,061 | C11: ±1,996 | D11: 6.9% | E11: ±1.0 | F11: 61,064 | G11: ±1,189 | H11: 6.0% | I11: ±0.1 | J11: 40,890 | K11: ±2,374 | L11: 6.7% | M11: ±0.4 | N11: 116,357 | O11: ±3,572 | P11: 6.5% | Q11: ±0.2
A12: 20 to 24 years | B12: 15,814 | C12: ±2,259 | D12: 7.7% | E12: ±1.1 | F12: 66,700 | G12: ±1,344 | H12: 6.6% | I12: ±0.1 | J12: 43,304 | K12: ±2,682 | L12: 7.1% | M12: ±0.4 | N12: 124,463 | O12: ±4,187 | P12: 6.9% | Q12: ±0.2
A13: 25 to 34 years | B13: 30,929 | C13: ±2,804 | D13: 15.1% | E13: ±1.4 | F13: 160,763 | G13: ±1,230 | H13: 15.9% | I13: ±0.1 | J13: 95,829 | K13: ±4,096 | L13: 15.7% | M13: ±0.7 | N13: 254,180 | O13: ±3,724 | P13: 14.1% | Q13: ±0.2
A14: 35 to 44 years | B14: 27,450 | C14: ±2,892 | D14: 13.4% | E14: ±1.4 | F14: 143,029 | G14: ±1,584 | H14: 14.2% | I14: ±0.2 | J14: 79,860 | K14: ±3,095 | L14: 13.1% | M14: ±0.5 | N14: 256,324 | O14: ±3,798 | P14: 14.3% | Q14: ±0.2
A15: 45 to 54 years | B15: 23,044 | C15: ±2,235 | D15: 11.3% | E15: ±1.1 | F15: 115,247 | G15: ±1,292 | H15: 11.4% | I15: ±0.1 | J15: 66,290 | K15: ±3,039 | L15: 10.9% | M15: ±0.5 | N15: 197,594 | O15: ±3,209 | P15: 11.0% | Q15: ±0.2
... A35: Sex ratio (males per 100 females) | B35: 76.4 | C35: ±7.3 | D35: (X) | E35: (X) | F35: 76.1 | G35: ±1.5 | H35: (X) | I35: (X) | J35: 69.0 | K35: ±3.5 | L35: (X) | M35: (X) | N35: 78.0 | O35: ±1.2 | P35: (X) | Q35: (X)
A36: RACE
A37: Total population | B37: 204,793 | C37: ±68 | D37: 204,793 | E37: (X) | F37: 1,009,831 | G37: ±22 | H37: 1,009,831 | I37: (X) | J37: 610,936 | K37: ±64 | L37: 610,936 | M37: (X) | N37: 1,796,689 | O37: ±4,440 | P37: 1,796,689 | Q37: (X)
A38: One race | B38: 186,876 | C38: ±4,014 | D38: 91.3% | E38: ±2.0 | F38: 882,424 | G38: ±9,602 | H38: 87.4% | I38: ±1.0 | J38: 575,142 | K38: ±6,102 | L38: 94.1% | M38: ±1.0 | N38: 1,625,611 | O38: ±10,610 | P38: 90.5% | Q38: ±0.5
A39: Two or More Races | B39: 17,917 | C39: ±4,007 | D39: 8.7% | E39: ±2.0 | F39: 127,407 | G39: ±9,603 | H39: 12.6% | I39: ±1.0 | J39: 35,794 | K39: ±6,102 | L39: 5.9% | M39: ±1.0 | N39: 171,078 | O39: ±9,477 | P39: 9.5% | Q39: ±0.5
A40: One race | B40: 186,876 | C40: ±4,014 | D40: 91.3% | E40: ±2.0 | F40: 882,424 | G40: ±9,602 | H40: 87.4% | I40: ±1.0 | J40: 575,142 | K40: ±6,102 | L40: 94.1% | M40: ±1.0 | N40: 1,625,611 | O40: ±10,610 | P40: 90.5% | Q40: ±0.5
A41: White | B41: 92,710 | C41: ±5,496 | D41: 45.3% | E41: ±2.7 | F41: 491,430 | G41: ±7,139 | H41: 48.7% | I41: ±0.7 | J41: 149,320 | K41: ±6,980 | L41: 24.4% | M41: ±1.1 | N41: 966,508 | O41: ±6,511 | P41: 53.8% | Q41: ±0.3
A42: Egyptian | B42: 210 | C42: ±315 | D42: 0.1% | E42: ±0.2 | F42: 1,553 | G42: ±1,379 | H42: 0.2% | I42: ±0.1 | J42: 17 | K42: ±43 | L42: 0.0% | M42: ±0.1 | N42: 411 | O42: ±359 | P42: 0.0% | Q42: ±0.1
A43: English | B43: 18,199 | C43: ±4,545 | D43: 8.9% | E43: ±2.2 | F43: 73,104 | G43: ±8,574 | H43: 7.2% | I43: ±0.8 | J43: 27,371 | K43: ±4,692 | L43: 4.5% | M43: ±0.8 | N43: 172,918 | O43: ±10,253 | P43: 9.6% | Q43: ±0.6
A44: German | B44: 9,127 | C44: ±4,113 | D44: 4.5% | E44: ±2.0 | F44: 29,088 | G44: ±4,088 | H44: 2.9% | I44: ±0.4 | J44: 7,078 | K44: ±1,778 | L44: 1.2% | M44: ±0.3 | N44: 64,566 | O44: ±5,980 | P44: 3.6% | Q44: ±0.3
A45: Irish | B45: 4,914 | C45: ±1,388 | D45: 2.4% | E45: ±0.7 | F45: 32,383 | G45: ±4,323 | H45: 3.2% | I45: ±0.4 | J45: 10,822 | K45: ±2,411 | L45: 1.8% | M45: ±0.4 | N45: 60,763 | O45: ±5,639 | P45: 3.4% | Q45: ±0.3
A46: Italian | B46: 765 | C46: ±426 | D46: 0.4% | E46: ±0.2 | F46: 14,803 | G46: ±2,096 | H46: 1.5% | I46: ±0.2 | J46: 3,406 | K46: ±1,124 | L46: 0.6% | M46: ±0.2 | N46: 30,605 | O46: ±4,632 | P46: 1.7% | Q46: ±0.3
A47: Lebanese | B47: 0 | C47: ±213 | D47: 0.0% | E47: ±0.1 | F47: 694 | G47: ±495 | H47: 0.1% | I47: ±0.1 | J47: 162 | K47: ±212 | L47: 0.0% | M47: ±0.1 | N47: 894 | O47: ±474 | P47: 0.0% | Q47: ±0.1
A48: Other White | B48: 59,495 | C48: ±5,458 | D48: 29.1% | E48: ±2.7 | F48: 339,805 | G48: ±10,895 | H48: 33.6% | I48: ±1.1 | J48: 100,464 | K48: ±5,848 | L48: 16.4% | M48: ±1.0 | N48: 636,351 | O48: ±13,202 | P48: 35.4% | Q48: ±0.7
... A85: Black or African American and Some Other Race | B85: 552 | C85: ±611 | D85: 0.3% | E85: ±0.3 | F85: 6,234 | G85: ±2,050 | H85: 0.6% | I85: ±0.2 | J85: 881 | K85: ±1,011 | L85: 0.1% | M85: ±0.2 | N85: 7,989 | O85: ±2,706 | P85: 0.4% | Q85: ±0.2
A86: Race alone or in combination with one or more other races
A87: Total population | B87: 204,793 | C87: ±68 | D87: 204,793 | E87: (X) | F87: 1,009,831 | G87: ±22 | H87: 1,009,831 | I87: (X) | J87: 610,936 | K87: ±64 | L87: 610,936 | M87: (X) | N87: 1,796,689 | O87: ±4,440 | P87: 1,796,689 | Q87: (X)
A88: White | B88: 108,543 | C88: ±5,913 | D88: 53.0% | E88: ±2.9 | F88: 605,968 | G88: ±7,643 | H88: 60.0% | I88: ±0.8 | J88: 179,718 | K88: ±9,024 | L88: 29.4% | M88: ±1.5 | N88: 1,116,980 | O88: ±9,595 | P88: 62.2% | Q88: ±0.5
A89: Black or African American | B89: 84,157 | C89: ±6,120 | D89: 41.1% | E89: ±3.0 | F89: 335,384 | G89: ±3,943 | H89: 33.2% | I89: ±0.4 | J89: 391,660 | K89: ±7,547 | L89: 64.1% | M89: ±1.2 | N89: 598,571 | O89: ±5,816 | P89: 33.3% | Q89: ±0.3
A90: American Indian and Alaska Native | B90: 3,283 | C90: ±1,595 | D90: 1.6% | E90: ±0.8 | F90: 17,342 | G90: ±4,950 | H90: 1.7% | I90: ±0.5 | J90: 9,986 | K90: ±4,118 | L90: 1.6% | M90: ±0.7 | N90: 33,130 | O90: ±4,395 | P90: 1.8% | Q90: ±0.2
A91: Asian | B91: 8,229 | C91: ±1,571 | D91: 4.0% | E91: ±0.8 | F91: 72,041 | G91: ±2,800 | H91: 7.1% | I91: ±0.3 | J91: 13,977 | K91: ±2,807 | L91: 2.3% | M91: ±0.5 | N91: 114,679 | O91: ±3,665 | P91: 6.4% | Q91: ±0.2
A92: Native Hawaiian and Other Pacific Islander | B92: 433 | C92: ±430 | D92: 0.2% | E92: ±0.2 | F92: 1,852 | G92: ±476 | H92: 0.2% | I92: ±0.1 | J92: 1,005 | K92: ±911 | L92: 0.2% | M92: ±0.1 | N92: 6,324 | O92: ±1,960 | P92: 0.4% | Q92: ±0.1
A93: Some Other Race | B93: 19,549 | C93: ±3,655 | D93: 9.5% | E93: ±1.8 | F93: 115,118 | G93: ±8,392 | H93: 11.4% | I93: ±0.8 | J93: 54,742 | K93: ±6,823 | L93: 9.0% | M93: ±1.1 | N93: 118,882 | O93: ±6,208 | P93: 6.6% | Q93: ±0.3
A94: HISPANIC OR LATINO AND RACE
A95: Total population | B95: 204,793 | C95: ±68 | D95: 204,793 | E95: (X) | F95: 1,009,831 | G95: ±22 | H95: 1,009,831 | I95: (X) | J95: 610,936 | K95: ±64 | L95: 610,936 | M95: (X) | N95: 1,796,689 | O95: ±4,440 | P95: 1,796,689 | Q95: (X)
A96: Hispanic or Latino (of any race) | B96: 21,919 | C96: ±3,263 | D96: 10.7% | E96: ±1.6 | F96: 140,312 | G96: ±1,428 | H96: 13.9% | I96: ±0.1 | J96: 62,413 | K96: ±4,525 | L96: 10.2% | M96: ±0.7 | N96: 153,327 | O96: ±1,536 | P96: 8.5% | Q96: ±0.1
A97: Mexican | B97: 13,212 | C97: ±3,830 | D97: 6.5% | E97: ±1.9 | F97: 29,078 | G97: ±7,167 | H97: 2.9% | I97: ±0.7 | J97: 30,231 | K97: ±5,067 | L97: 4.9% | M97: ±0.8 | N97: 49,008 | O97: ±6,114 | P97: 2.7% | Q97: ±0.3
A98: Puerto Rican | B98: 1,108 | C98: ±1,061 | D98: 0.5% | E98: ±0.5 | F98: 38,304 | G98: ±6,294 | H98: 3.8% | I98: ±0.6 | J98: 2,197 | K98: ±1,383 | L98: 0.4% | M98: ±0.2 | N98: 38,161 | O98: ±5,399 | P98: 2.1% | Q98: ±0.3
A99: Cuban | B99: 144 | C99: ±187 | D99: 0.1% | E99: ±0.1 | F99: 22,456 | G99: ±5,414 | H99: 2.2% | I99: ±0.5 | J99: 890 | K99: ±671 | L99: 0.1% | M99: ±0.1 | N99: 6,987 | O99: ±2,262 | P99: 0.4% | Q99: ±0.1
A100: Other Hispanic or Latino | B100: 7,455 | C100: ±3,147 | D100: 3.6% | E100: ±1.5 | F100: 50,474 | G100: ±7,392 | H100: 5.0% | I100: ±0.7 | J100: 29,095 | K100: ±6,181 | L100: 4.8% | M100: ±1.0 | N100: 59,171 | O100: ±5,813 | P100: 3.3% | Q100: ±0.3
A101: Not Hispanic or Latino | B101: 182,874 | C101: ±3,264 | D101: 89.3% | E101: ±1.6 | F101: 869,519 | G101: ±1,428 | H101: 86.1% | I101: ±0.1 | J101: 548,523 | K101: ±4,527 | L101: 89.8% | M101: ±0.7 | N101: 1,643,362 | O101: ±4,483 | P101: 91.5% | Q101: ±0.1
A102: White alone | B102: 90,838 | C102: ±5,311 | D102: 44.4% | E102: ±2.6 | F102: 460,929 | G102: ±5,122 | H102: 45.6% | I102: ±0.5 | J102: 141,763 | K102: ±6,519 | L102: 23.2% | M102: ±1.1 | N102: 934,738 | O102: ±4,432 | P102: 52.0% | Q102: ±0.2
A103: Black or African American alone | B103: 78,135 | C103: ±6,213 | D103: 38.2% | E103: ±3.0 | F103: 291,228 | G103: ±6,162 | H103: 28.8% | I103: ±0.6 | J103: 376,362 | K103: ±7,396 | L103: 61.6% | M103: ±1.2 | N103: 515,771 | O103: ±7,513 | P103: 28.7% | Q103: ±0.4
A104: American Indian and Alaska Native alone | B104: 291 | C104: ±244 | D104: 0.1% | E104: ±0.1 | F104: 545 | G104: ±269 | H104: 0.1% | I104: ±0.1 | J104: 522 | K104: ±329 | L104: 0.1% | M104: ±0.1 | N104: 3,140 | O104: ±989 | P104: 0.2% | Q104: ±0.1
A105: Asian alone | B105: 5,252 | C105: ±1,429 | D105: 2.6% | E105: ±0.7 | F105: 51,959 | G105: ±3,731 | H105: 5.1% | I105: ±0.4 | J105: 8,888 | K105: ±2,108 | L105: 1.5% | M105: ±0.3 | N105: 70,954 | O105: ±4,084 | P105: 3.9% | Q105: ±0.2
A106: Native Hawaiian and Other Pacific Islander alone | B106: 304 | C106: ±393 | D106: 0.1% | E106: ±0.2 | F106: 776 | G106: ±329 | H106: 0.1% | I106: ±0.1 | J106: 367 | K106: ±501 | L106: 0.1% | M106: ±0.1 | N106: 1,529 | O106: ±924 | P106: 0.1% | Q106: ±0.1
... A111: Total housing units | B111: 99,014 | C111: ±2,978 | D111: (X) | E111: (X) | F111: 449,941 | G111: ±1,719 | H111: (X) | I111: (X) | J111: 291,759 | K111: ±3,489 | L111: (X) | M111: (X) | N111: 774,453 | O111: ±2,344 | P111: (X) | Q111: (X)
A112: CITIZEN, VOTING AGE POPULATION
A113: Citizen, 18 and over population | B113: 139,676 | C113: ±4,237 | D113: 139,676 | E113: (X) | F113: 735,123 | G113: ±8,055 | H113: 735,123 | I113: (X) | J113: 427,520 | K113: ±4,831 | L113: 427,520 | M113: (X) | N113: 1,357,412 | O113: ±5,650 | P113: 1,357,412 | Q113: (X)
A114: Male | B114: 63,845 | C114: ±3,381 | D114: 45.7% | E114: ±1.7 | F114: 349,183 | G114: ±5,379 | H114: 47.5% | I114: ±0.4 | J114: 193,764 | K114: ±4,043 | L114: 45.3% | M114: ±0.7 | N114: 657,949 | O114: ±3,918 | P114: 48.5% | Q114: ±0.2
A115: Female | B115: 75,831 | C115: ±2,911 | D115: 54.3% | E115: ±1.7 | F115: 385,940 | G115: ±4,667 | H115: 52.5% | I115: ±0.4 | J115: 233,756 | K115: ±3,636 | L115: 54.7% | M115: ±0.7 | N115: 699,463 | O115: ±3,516 | P115: 51.5% | Q115: ±0.2

Sheet Data (2020)
B1: Little Rock city, Arkansas | F1: Jacksonville city, Florida | J1: Memphis city, Tennessee | N1: Virginia Beach-Norfolk-Newport News, VA-NC Metro Area
A2: Label | B2: Estimate | C2: Margin of Error | D2: Percent | E2: Percent Margin of Error | F2: Estimate | G2: Margin of Error | H2: Percent | I2: Percent Margin of Error | J2: Estimate | K2: Margin of Error | L2: Percent | M2: Percent Margin of Error | N2: Estimate | O2: Margin of Error | P2: Percent | Q2: Percent Margin of Error
A3: HOUSING OCCUPANCY
A4: Total housing units | B4: 96,399 | C4: ±1,083 | D4: 96,399 | E4: (X) | F4: 389,130 | G4: ±833 | H4: 389,130 | I4: (X) | J4: 299,599 | K4: ±1,427 | L4: 299,599 | M4: (X) | N4: 739,434 | O4: ±745 | P4: 739,434 | Q4: (X)
A5: Occupied housing units | B5: 83,525 | C5: ±1,328 | D5: 86.6% | E5: ±1.0 | F5: 348,809 | G5: ±2,342 | H5: 89.6% | I5: ±0.5 | J5: 255,756 | K5: ±2,087 | L5: 85.4% | M5: ±0.5 | N5: 672,053 | O5: ±2,310 | P5: 90.9% | Q5: ±0.3
A6: Vacant housing units | B6: 12,874 | C6: ±992 | D6: 13.4% | E6: ±1.0 | F6: 40,321 | G6: ±2,064 | H6: 10.4% | I6: ±0.5 | J6: 43,843 | K6: ±1,560 | L6: 14.6% | M6: ±0.5 | N6: 67,381 | O6: ±2,040 | P6: 9.1% | Q6: ±0.3
A7: Homeowner vacancy rate | B7: 2.4 | C7: ±0.6 | D7: (X) | E7: (X) | F7: 2.0 | G7: ±0.3 | H7: (X) | I7: (X) | J7: 1.2 | K7: ±0.2 | L7: (X) | M7: (X) | N7: 1.8 | O7: ±0.2 | P7: (X) | Q7: (X)
A8: Rental vacancy rate | B8: 12.0 | C8: ±1.5 | D8: (X) | E8: (X) | F8: 6.6 | G8: ±0.7 | H8: (X) | I8: (X) | J8: 8.3 | K8: ±0.6 | L8: (X) | M8: (X) | N8: 6.8 | O8: ±0.5 | P8: (X) | Q8: (X)
A9: UNITS IN STRUCTURE
A10: Total housing units | B10: 96,399 | C10: ±1,083 | D10: 96,399 | E10: (X) | F10: 389,130 | G10: ±833 | H10: 389,130 | I10: (X) | J10: 299,599 | K10: ±1,427 | L10: 299,599 | M10: (X) | N10: 739,434 | O10: ±745 | P10: 739,434 | Q10: (X)
A11: 1-unit, detached | B11: 60,153 | C11: ±1,282 | D11: 62.4% | E11: ±1.1 | F11: 235,668 | G11: ±2,634 | H11: 60.6% | I11: ±0.7 | J11: 180,207 | K11: ±2,327 | L11: 60.1% | M11: ±0.7 | N11: 451,678 | O11: ±3,029 | P11: 61.1% | Q11: ±0.4
A12: 1-unit, attached | B12: 1,472 | C12: ±290 | D12: 1.5% | E12: ±0.3 | F12: 18,749 | G12: ±1,215 | H12: 4.8% | I12: ±0.3 | J12: 14,901 | K12: ±1,129 | L12: 5.0% | M12: ±0.4 | N12: 81,661 | O12: ±2,021 | P12: 11.0% | Q12: ±0.3
A13: 2 units | B13: 3,000 | C13: ±596 | D13: 3.1% | E13: ±0.6 | F13: 5,972 | G13: ±588 | H13: 1.5% | I13: ±0.2 | J13: 7,307 | K13: ±728 | L13: 2.4% | M13: ±0.2 | N13: 15,944 | O13: ±964 | P13: 2.2% | Q13: ±0.1
A14: 3 or 4 units | B14: 4,258 | C14: ±751 | D14: 4.4% | E14: ±0.8 | F14: 16,330 | G14: ±1,417 | H14: 4.2% | I14: ±0.4 | J14: 20,105 | K14: ±1,097 | L14: 6.7% | M14: ±0.4 | N14: 36,038 | O14: ±1,590 | P14: 4.9% | Q14: ±0.2
A15: 5 to 9 units | B15: 7,895 | C15: ±1,010 | D15: 8.2% | E15: ±1.0 | F15: 21,669 | G15: ±1,295 | H15: 5.6% | I15: ±0.3 | J15: 31,713 | K15: ±1,662 | L15: 10.6% | M15: ±0.6 | N15: 52,780 | O15: ±2,049 | P15: 7.1% | Q15: ±0.3
A16: 10 to 19 units | B16: 8,167 | C16: ±906 | D16: 8.5% | E16: ±0.9 | F16: 32,577 | G16: ±1,859 | H16: 8.4% | I16: ±0.5 | J16: 19,152 | K16: ±1,191 | L16: 6.4% | M16: ±0.4 | N16: 35,911 | O16: ±1,473 | P16: 4.9% | Q16: ±0.2
A17: 20 or more units | B17: 10,080 | C17: ±808 | D17: 10.5% | E17: ±0.8 | F17: 39,895 | G17: ±1,725 | H17: 10.3% | I17: ±0.4 | J17: 23,092 | K17: ±949 | L17: 7.7% | M17: ±0.3 | N17: 45,148 | O17: ±1,491 | P17: 6.1% | Q17: ±0.2
A18: Mobile home | B18: 1,290 | C18: ±292 | D18: 1.3% | E18: ±0.3 | F18: 18,081 | G18: ±1,195 | H18: 4.6% | I18: ±0.3 | J18: 3,010 | K18: ±412 | L18: 1.0% | M18: ±0.1 | N18: 19,952 | O18: ±946 | P18: 2.7% | Q18: ±0.1
A19: Boat, RV, van, etc. | B19: 84 | C19: ±115 | D19: 0.1% | E19: ±0.1 | F19: 189 | G19: ±90 | H19: 0.0% | I19: ±0.1 | J19: 112 | K19: ±69 | L19: 0.0% | M19: ±0.1 | N19: 322 | O19: ±145 | P19: 0.0% | Q19: ±0.1
A20: YEAR STRUCTURE BUILT
A21: Total housing units | B21: 96,399 | C21: ±1,083 | D21: 96,399 | E21: (X) | F21: 389,130 | G21: ±833 | H21: 389,130 | I21: (X) | J21: 299,599 | K21: ±1,427 | L21: 299,599 | M21: (X) | N21: 739,434 | O21: ±745 | P21: 739,434 | Q21: (X)
A22: Built 2014 or later | B22: 3,748 | C22: ±677 | D22: 3.9% | E22: ±0.7 | F22: 17,808 | G22: ±1,522 | H22: 4.6% | I22: ±0.4 | J22: 4,130 | K22: ±616 | L22: 1.4% | M22: ±0.2 | N22: 27,376 | O22: ±1,309 | P22: 3.7% | Q22: ±0.2
A23: Built 2010 to 2013 | B23: 3,144 | C23: ±441 | D23: 3.3% | E23: ±0.5 | F23: 11,357 | G23: ±1,070 | H23: 2.9% | I23: ±0.3 | J23: 3,708 | K23: ±657 | L23: 1.2% | M23: ±0.2 | N23: 23,486 | O23: ±1,284 | P23: 3.2% | Q23: ±0.2
A24: Built 2000 to 2009 | B24: 10,569 | C24: ±861 | D24: 11.0% | E24: ±0.9 | F24: 71,288 | G24: ±2,358 | H24: 18.3% | I24: ±0.6 | J24: 19,487 | K24: ±1,210 | L24: 6.5% | M24: ±0.4 | N24: 93,027 | O24: ±2,283 | P24: 12.6% | Q24: ±0.3
A25: Built 1990 to 1999 | B25: 12,225 | C25: ±973 | D25: 12.7% | E25: ±1.0 | F25: 60,060 | G25: ±2,229 | H25: 15.4% | I25: ±0.6 | J25: 30,231 | K25: ±1,392 | L25: 10.1% | M25: ±0.5 | N25: 113,391 | O25: ±2,181 | P25: 15.3% | Q25: ±0.3
A26: Built 1980 to 1989 | B26: 13,676 | C26: ±950 | D26: 14.2% | E26: ±1.0 | F26: 60,199 | G26: ±2,188 | H26: 15.5% | I26: ±0.6 | J26: 36,462 | K26: ±1,345 | L26: 12.2% | M26: ±0.4 | N26: 138,152 | O26: ±2,607 | P26: 18.7% | Q26: ±0.4
A27: Built 1970 to 1979 | B27: 18,612 | C27: ±1,113 | D27: 19.3% | E27: ±1.1 | F27: 48,810 | G27: ±2,147 | H27: 12.5% | I27: ±0.5 | J27: 53,778 | K27: ±1,711 | L27: 17.9% | M27: ±0.6 | N27: 115,186 | O27: ±2,734 | P27: 15.6% | Q27: ±0.4
A28: Built 1960 to 1969 | B28: 13,592 | C28: ±833 | D28: 14.1% | E28: ±0.8 | F28: 38,773 | G28: ±1,850 | H28: 10.0% | I28: ±0.5 | J28: 43,128 | K28: ±1,493 | L28: 14.4% | M28: ±0.5 | N28: 85,704 | O28: ±1,844 | P28: 11.6% | Q28: ±0.2
A29: Built 1950 to 1959 | B29: 8,820 | C29: ±698 | D29: 9.1% | E29: ±0.7 | F29: 42,500 | G29: ±1,644 | H29: 10.9% | I29: ±0.4 | J29: 57,599 | K29: ±1,541 | L29: 19.2% | M29: ±0.5 | N29: 70,246 | O29: ±1,741 | P29: 9.5% | Q29: ±0.2
A30: Built 1940 to 1949 | B30: 4,949 | C30: ±672 | D30: 5.1% | E30: ±0.7 | F30: 18,394 | G30: ±1,114 | H30: 4.7% | I30: ±0.3 | J30: 28,090 | K30: ±1,432 | L30: 9.4% | M30: ±0.5 | N30: 30,657 | O30: ±1,308 | P30: 4.1% | Q30: ±0.2
A31: Built 1939 or earlier | B31: 7,064 | C31: ±504 | D31: 7.3% | E31: ±0.5 | F31: 19,941 | G31: ±1,178 | H31: 5.1% | I31: ±0.3 | J31: 22,986 | K31: ±1,049 | L31: 7.7% | M31: ±0.3 | N31: 42,209 | O31: ±1,240 | P31: 5.7% | Q31: ±0.2
A32: ROOMS
A33: Total housing units | B33: 96,399 | C33: ±1,083 | D33: 96,399 | E33: (X) | F33: 389,130 | G33: ±833 | H33: 389,130 | I33: (X) | J33: 299,599 | K33: ±1,427 | L33: 299,599 | M33: (X) | N33: 739,434 | O33: ±745 | P33: 739,434 | Q33: (X)
A34: 1 room | B34: 3,240 | C34: ±503 | D34: 3.4% | E34: ±0.5 | F34: 6,706 | G34: ±673 | H34: 1.7% | I34: ±0.2 | J34: 5,767 | K34: ±687 | L34: 1.9% | M34: ±0.2 | N34: 9,647 | O34: ±732 | P34: 1.3% | Q34: ±0.1
A35: 2 rooms | B35: 3,127 | C35: ±504 | D35: 3.2% | E35: ±0.5 | F35: 10,731 | G35: ±1,102 | H35: 2.8% | I35: ±0.3 | J35: 3,538 | K35: ±443 | L35: 1.2% | M35: ±0.1 | N35: 10,855 | O35: ±843 | P35: 1.5% | Q35: ±0.1
A36: 3 rooms | B36: 9,734 | C36: ±998 | D36: 10.1% | E36: ±1.0 | F36: 35,828 | G36: ±1,773 | H36: 9.2% | I36: ±0.5 | J36: 29,311 | K36: ±1,376 | L36: 9.8% | M36: ±0.5 | N36: 46,004 | O36: ±2,031 | P36: 6.2% | Q36: ±0.3
A37: 4 rooms | B37: 16,504 | C37: ±1,293 | D37: 17.1% | E37: ±1.4 | F37: 62,875 | G37: ±2,149 | H37: 16.2% | I37: ±0.5 | J37: 57,458 | K37: ±1,726 | L37: 19.2% | M37: ±0.6 | N37: 110,104 | O37: ±2,437 | P37: 14.9% | Q37: ±0.3
A38: 5 rooms | B38: 19,409 | C38: ±1,319 | D38: 20.1% | E38: ±1.3 | F38: 77,339 | G38: ±2,728 | H38: 19.9% | I38: ±0.7 | J38: 68,089 | K38: ±1,898 | L38: 22.7% | M38: ±0.7 | N38: 127,937 | O38: ±2,658 | P38: 17.3% | Q38: ±0.4
A39: 6 rooms | B39: 17,029 | C39: ±1,088 | D39: 17.7% | E39: ±1.1 | F39: 78,011 | G39: ±2,358 | H39: 20.0% | I39: ±0.6 | J39: 59,742 | K39: ±1,950 | L39: 19.9% | M39: ±0.6 | N39: 131,006 | O39: ±2,520 | P39: 17.7% | Q39: ±0.3
A40: 7 rooms | B40: 10,689 | C40: ±806 | D40: 11.1% | E40: ±0.9 | F40: 50,848 | G40: ±1,802 | H40: 13.1% | I40: ±0.5 | J40: 33,877 | K40: ±1,594 | L40: 11.3% | M40: ±0.5 | N40: 105,759 | O40: ±2,258 | P40: 14.3% | Q40: ±0.3
A41: 8 rooms | B41: 6,706 | C41: ±585 | D41: 7.0% | E41: ±0.6 | F41: 34,216 | G41: ±1,529 | H41: 8.8% | I41: ±0.4 | J41: 21,296 | K41: ±1,176 | L41: 7.1% | M41: ±0.4 | N41: 89,714 | O41: ±2,168 | P41: 12.1% | Q41: ±0.3
A42: 9 rooms or more | B42: 9,961 | C42: ±724 | D42: 10.3% | E42: ±0.7 | F42: 32,576 | G42: ±1,627 | H42: 8.4% | I42: ±0.4 | J42: 20,521 | K42: ±1,049 | L42: 6.8% | M42: ±0.3 | N42: 108,408 | O42: ±2,441 | P42: 14.7% | Q42: ±0.3
A43: Median rooms | B43: 5.3 | C43: ±0.1 | D43: (X) | E43: (X) | F43: 5.5 | G43: ±0.1 | H43: (X) | I43: (X) | J43: 5.3 | K43: ±0.1 | L43: (X) | M43: (X) | N43: 6.0 | O43: ±0.1 | P43: (X) | Q43: (X)
A44: BEDROOMS
A45: Total housing units | B45: 96,399 | C45: ±1,083 | D45: 96,399 | E45: (X) | F45: 389,130 | G45: ±833 | H45: 389,130 | I45: (X) | J45: 299,599 | K45: ±1,427 | L45: 299,599 | M45: (X) | N45: 739,434 | O45: ±745 | P45: 739,434 | Q45: (X)
A46: No bedroom | B46: 3,330 | C46: ±505 | D46: 3.5% | E46: ±0.5 | F46: 7,261 | G46: ±708 | H46: 1.9% | I46: ±0.2 | J46: 6,162 | K46: ±700 | L46: 2.1% | M46: ±0.2 | N46: 10,365 | O46: ±734 | P46: 1.4% | Q46: ±0.1
A47: 1 bedroom | B47: 12,971 | C47: ±987 | D47: 13.5% | E47: ±1.0 | F47: 42,285 | G47: ±2,239 | H47: 10.9% | I47: ±0.6 | J47: 36,568 | K47: ±1,584 | L47: 12.2% | M47: ±0.5 | N47: 51,295 | O47: ±1,639 | P47: 6.9% | Q47: ±0.2
A48: 2 bedrooms | B48: 26,236 | C48: ±1,454 | D48: 27.2% | E48: ±1.5 | F48: 94,174 | G48: ±2,682 | H48: 24.2% | I48: ±0.7 | J48: 94,491 | K48: ±2,132 | L48: 31.5% | M48: ±0.7 | N48: 178,471 | O48: ±2,588 | P48: 24.1% | Q48: ±0.3
A49: 3 bedrooms | B49: 37,017 | C49: ±1,446 | D49: 38.4% | E49: ±1.4 | F49: 168,416 | G49: ±2,873 | H49: 43.3% | I49: ±0.7 | J49: 118,846 | K49: ±2,204 | L49: 39.7% | M49: ±0.7 | N49: 295,508 | O49: ±2,901 | P49: 40.0% | Q49: ±0.4
A50: 4 bedrooms | B50: 13,669 | C50: ±862 | D50: 14.2% | E50: ±0.9 | F50: 66,228 | G50: ±2,103 | H50: 17.0% | I50: ±0.5 | J50: 35,070 | K50: ±1,374 | L50: 11.7% | M50: ±0.5 | N50: 162,398 | O50: ±2,662 | P50: 22.0% | Q50: ±0.4
A51: 5 or more bedrooms | B51: 3,176 | C51: ±394 | D51: 3.3% | E51: ±0.4 | F51: 10,766 | G51: ±1,000 | H51: 2.8% | I51: ±0.3 | J51: 8,462 | K51: ±679 | L51: 2.8% | M51: ±0.2 | N51: 41,397 | O51: ±1,275 | P51: 5.6% | Q51: ±0.2
A52: HOUSING TENURE
A53: Occupied housing units | B53: 83,525 | C53: ±1,328 | D53: 83,525 | E53: (X) | F53: 348,809 | G53: ±2,342 | H53: 348,809 | I53: (X) | J53: 255,756 | K53: ±2,087 | L53: 255,756 | M53: (X) | N53: 672,053 | O53: ±2,310 | P53: 672,053 | Q53: (X)
A54: Owner-occupied | B54: 45,625 | C54: ±1,464 | D54: 54.6% | E54: ±1.5 | F54: 196,649 | G54: ±2,556 | H54: 56.4% | I54: ±0.7 | J54: 118,235 | K54: ±2,383 | L54: 46.2% | M54: ±0.8 | N54: 418,960 | O54: ±3,643 | P54: 62.3% | Q54: ±0.5
A55: Renter-occupied | B55: 37,900 | C55: ±1,341 | D55: 45.4% | E55: ±1.5 | F55: 152,160 | G55: ±2,801 | H55: 43.6% | I55: ±0.7 | J55: 137,521 | K55: ±2,353 | L55: 53.8% | M55: ±0.8 | N55: 253,093 | O55: ±3,104 | P55: 37.7% | Q55: ±0.5
A56: Average household size of owner-occupied unit | B56: 2.45 | C56: ±0.05 | D56: (X) | E56: (X) | F56: 2.62 | G56: ±0.03 | H56: (X) | I56: (X) | J56: 2.53 | K56: ±0.04 | L56: (X) | M56: (X) | N56: 2.60 | O56: ±0.01 | P56: (X) | Q56: (X)
A57: Average household size of renter-occupied unit | B57: 2.18 | C57: ±0.06 | D57: (X) | E57: (X) | F57: 2.41 | G57: ±0.03 | H57: (X) | I57: (X) | J57: 2.45 | K57: ±0.03 | L57: (X) | M57: (X) | N57: 2.41 | O57: ±0.02 | P57: (X) | Q57: (X)
A58: YEAR HOUSEHOLDER MOVED INTO UNIT
A59: Occupied housing units | B59: 83,525 | C59: ±1,328 | D59: 83,525 | E59: (X) | F59: 348,809 | G59: ±2,342 | H59: 348,809 | I59: (X) | J59: 255,756 | K59: ±2,087 | L59: 255,756 | M59: (X) | N59: 672,053 | O59: ±2,310 | P59: 672,053 | Q59: (X)
A60: Moved in 2019 or later | B60: 4,591 | C60: ±717 | D60: 5.5% | E60: ±0.8 | F60: 23,706 | G60: ±1,736 | H60: 6.8% | I60: ±0.5 | J60: 16,657 | K60: ±1,265 | L60: 6.5% | M60: ±0.5 | N60: 37,905 | O60: ±1,918 | P60: 5.6% | Q60: ±0.3
A61: Moved in 2015 to 2018 | B61: 30,175 | C61: ±1,363 | D61: 36.1% | E61: ±1.7 | F61: 126,954 | G61: ±2,509 | H61: 36.4% | I61: ±0.7 | J61: 86,940 | K61: ±2,366 | L61: 34.0% | M61: ±0.8 | N61: 211,136 | O61: ±2,732 | P61: 31.4% | Q61: ±0.4
A62: Moved in 2010 to 2014 | B62: 16,436 | C62: ±941 | D62: 19.7% | E62: ±1.1 | F62: 66,362 | G62: ±2,353 | H62: 19.0% | I62: ±0.7 | J62: 50,169 | K62: ±1,822 | L62: 19.6% | M62: ±0.7 | N62: 124,166 | O62: ±2,485 | P62: 18.5% | Q62: ±0.4
A63: Moved in 2000 to 2009 | B63: 17,222 | C63: ±1,108 | D63: 20.6% | E63: ±1.2 | F63: 64,860 | G63: ±1,888 | H63: 18.6% | I63: ±0.5 | J63: 44,273 | K63: ±1,576 | L63: 17.3% | M63: ±0.6 | N63: 137,823 | O63: ±2,531 | P63: 20.5% | Q63: ±0.4
A64: Moved in 1990 to 1999 | B64: 8,298 | C64: ±710 | D64: 9.9% | E64: ±0.8 | F64: 33,735 | G64: ±1,394 | H64: 9.7% | I64: ±0.4 | J64: 27,097 | K64: ±1,092 | L64: 10.6% | M64: ±0.4 | N64: 81,213 | O64: ±1,996 | P64: 12.1% | Q64: ±0.3
A65: Moved in 1989 and earlier | B65: 6,803 | C65: ±747 | D65: 8.1% | E65: ±0.9 | F65: 33,192 | G65: ±1,380 | H65: 9.5% | I65: ±0.4 | J65: 30,620 | K65: ±1,205 | L65: 12.0% | M65: ±0.5 | N65: 79,810 | O65: ±1,869 | P65: 11.9% | Q65: ±0.3
A66: VEHICLES AVAILABLE
A67: Occupied housing units | B67: 83,525 | C67: ±1,328 | D67: 83,525 | E67: (X) | F67: 348,809 | G67: ±2,342 | H67: 348,809 | I67: (X) | J67: 255,756 | K67: ±2,087 | L67: 255,756 | M67: (X) | N67: 672,053 | O67: ±2,310 | P67: 672,053 | Q67: (X)
A68: No vehicles available | B68: 6,865 | C68: ±751 | D68: 8.2% | E68: ±0.9 | F68: 27,098 | G68: ±1,407 | H68: 7.8% | I68: ±0.4 | J68: 28,470 | K68: ±1,292 | L68: 11.1% | M68: ±0.5 | N68: 44,687 | O68: ±1,661 | P68: 6.6% | Q68: ±0.2
A69: 1 vehicle available | B69: 34,498 | C69: ±1,506 | D69: 41.3% | E69: ±1.6 | F69: 137,403 | G69: ±2,772 | H69: 39.4% | I69: ±0.7 | J69: 113,452 | K69: ±2,513 | L69: 44.4% | M69: ±0.9 | N69: 206,793 | O69: ±3,053 | P69: 30.8% | Q69: ±0.5
A70: 2 vehicles available | B70: 29,430 | C70: ±1,431 | D70: 35.2% | E70: ±1.6 | F70: 130,715 | G70: ±2,489 | H70: 37.5% | I70: ±0.7 | J70: 78,437 | K70: ±1,944 | L70: 30.7% | M70: ±0.8 | N70: 256,379 | O70: ±3,334 | P70: 38.1% | Q70: ±0.5
A71: 3 or more vehicles available | B71: 12,732 | C71: ±885 | D71: 15.2% | E71: ±1.1 | F71: 53,593 | G71: ±1,867 | H71: 15.4% | I71: ±0.5 | J71: 35,397 | K71: ±1,528 | L71: 13.8% | M71: ±0.6 | N71: 164,194 | O71: ±2,567 | P71: 24.4% | Q71: ±0.4
A72: HOUSE HEATING FUEL
A73: Occupied housing units | B73: 83,525 | C73: ±1,328 | D73: 83,525 | E73: (X) | F73: 348,809 | G73: ±2,342 | H73: 348,809 | I73: (X) | J73: 255,756 | K73: ±2,087 | L73: 255,756 | M73: (X) | N73: 672,053 | O73: ±2,310 | P73: 672,053 | Q73: (X)
A74: Utility gas | B74: 41,454 | C74: ±1,217 | D74: 49.6% | E74: ±1.4 | F74: 8,683 | G74: ±845 | H74: 2.5% | I74: ±0.2 | J74: 122,062 | K74: ±2,422 | L74: 47.7% | M74: ±0.8 | N74: 247,558 | O74: ±2,615 | P74: 36.8% | Q74: ±0.4
A75: Bottled, tank, or LP gas | B75: 992 | C75: ±255 | D75: 1.2% | E75: ±0.3 | F75: 2,893 | G75: ±434 | H75: 0.8% | I75: ±0.1 | J75: 2,118 | K75: ±448 | L75: 0.8% | M75: ±0.2 | N75: 15,911 | O75: ±845 | P75: 2.4% | Q75: ±0.1
A76: Electricity | B76: 40,414 | C76: ±1,473 | D76: 48.4% | E76: ±1.4 | F76: 332,003 | G76: ±2,454 | H76: 95.2% | I76: ±0.3 | J76: 129,416 | K76: ±2,022 | L76: 50.6% | M76: ±0.8 | N76: 383,959 | O76: ±2,901 | P76: 57.1% | Q76: ±0.4
A77: Fuel oil, kerosene, etc. | B77: 67 | C77: ±59 | D77: 0.1% | E77: ±0.1 | F77: 1,156 | G77: ±374 | H77: 0.3% | I77: ±0.1 | J77: 179 | K77: ±80 | L77: 0.1% | M77: ±0.1 | N77: 15,765 | O77: ±895 | P77: 2.3% | Q77: ±0.1
A78: Coal or coke | B78: 0 | C78: ±29 | D78: 0.0% | E78: ±0.1 | F78: 82 | G78: ±66 | H78: 0.0% | I78: ±0.1 | J78: 44 | K78: ±39 | L78: 0.0% | M78: ±0.1 | N78: 192 | O78: ±106 | P78: 0.0% | Q78: ±0.1
A79: Wood | B79: 144 | C79: ±77 | D79: 0.2% | E79: ±0.1 | F79: 326 | G79: ±104 | H79: 0.1% | I79: ±0.1 | J79: 298 | K79: ±138 | L79: 0.1% | M79: ±0.1 | N79: 3,266 | O79: ±393 | P79: 0.5% | Q79: ±0.1
A80: Solar energy | B80: 0 | C80: ±29 | D80: 0.0% | E80: ±0.1 | F80: 231 | G80: ±115 | H80: 0.1% | I80: ±0.1 | J80: 72 | K80: ±91 | L80: 0.0% | M80: ±0.1 | N80: 315 | O80: ±201 | P80: 0.0% | Q80: ±0.1
A81: Other fuel | B81: 0 | C81: ±29 | D81: 0.0% | E81: ±0.1 | F81: 162 | G81: ±72 | H81: 0.0% | I81: ±0.1 | J81: 320 | K81: ±150 | L81: 0.1% | M81: ±0.1 | N81: 1,601 | O81: ±244 | P81: 0.2% | Q81: ±0.1
A82: No fuel used | B82: 454 | C82: ±216 | D82: 0.5% | E82: ±0.3 | F82: 3,273 | G82: ±591 | H82: 0.9% | I82: ±0.2 | J82: 1,247 | K82: ±254 | L82: 0.5% | M82: ±0.1 | N82: 3,486 | O82: ±495 | P82: 0.5% | Q82: ±0.1
A83: SELECTED CHARACTERISTICS
A84: Occupied housing units | B84: 83,525 | C84: ±1,328 | D84: 83,525 | E84: (X) | F84: 348,809 | G84: ±2,342 | H84: 348,809 | I84: (X) | J84: 255,756 | K84: ±2,087 | L84: 255,756 | M84: (X) | N84: 672,053 | O84: ±2,310 | P84: 672,053 | Q84: (X)
A85: Lacking complete plumbing facilities | B85: 262 | C85: ±161 | D85: 0.3% | E85: ±0.2 | F85: 782 | G85: ±235 | H85: 0.2% | I85: ±0.1 | J85: 879 | K85: ±310 | L85: 0.3% | M85: ±0.1 | N85: 2,958 | O85: ±512 | P85: 0.4% | Q85: ±0.1
A86: Lacking complete kitchen facilities | B86: 691 | C86: ±220 | D86: 0.8% | E86: ±0.3 | F86: 2,073 | G86: ±317 | H86: 0.6% | I86: ±0.1 | J86: 2,288 | K86: ±629 | L86: 0.9% | M86: ±0.2 | N86: 3,398 | O86: ±484 | P86: 0.5% | Q86: ±0.1
A87: No telephone service available | B87: 1,512 | C87: ±359 | D87: 1.8% | E87: ±0.4 | F87: 5,453 | G87: ±595 | H87: 1.6% | I87: ±0.2 | J87: 4,641 | K87: ±542 | L87: 1.8% | M87: ±0.2 | N87: 7,687 | O87: ±588 | P87: 1.1% | Q87: ±0.1
A88: OCCUPANTS PER ROOM
A89: Occupied housing units | B89: 83,525 | C89: ±1,328 | D89: 83,525 | E89: (X) | F89: 348,809 | G89: ±2,342 | H89: 348,809 | I89: (X) | J89: 255,756 | K89: ±2,087 | L89: 255,756 | M89: (X) | N89: 672,053 | O89: ±2,310 | P89: 672,053 | Q89: (X)
A90: 1.00 or less | B90: 81,423 | C90: ±1,374 | D90: 97.5% | E90: ±0.4 | F90: 341,005 | G90: ±2,408 | H90: 97.8% | I90: ±0.2 | J90: 249,171 | K90: ±2,197 | L90: 97.4% | M90: ±0.3 | N90: 661,233 | O90: ±2,703 | P90: 98.4% | Q90: ±0.2
A91: 1.01 to 1.50 | B91: 1,430 | C91: ±350 | D91: 1.7% | E91: ±0.4 | F91: 5,767 | G91: ±697 | H91: 1.7% | I91: ±0.2 | J91: 5,133 | K91: ±538 | L91: 2.0% | M91: ±0.2 | N91: 7,512 | O91: ±905 | P91: 1.1% | Q91: ±0.1
A92: 1.51 or more | B92: 672 | C92: ±239 | D92: 0.8% | E92: ±0.3 | F92: 2,037 | G92: ±382 | H92: 0.6% | I92: ±0.1 | J92: 1,452 | K92: ±422 | L92: 0.6% | M92: ±0.2 | N92: 3,308 | O92: ±501 | P92: 0.5% | Q92: ±0.1
A93: VALUE
A94: Owner-occupied units | B94: 45,625 | C94: ±1,464 | D94: 45,625 | E94: (X) | F94: 196,649 | G94: ±2,556 | H94: 196,649 | I94: (X) | J94: 118,235 | K94: ±2,383 | L94: 118,235 | M94: (X) | N94: 418,960 | O94: ±3,643 | P94: 418,960 | Q94: (X)
A95: Less than $50,000 | B95: 2,764 | C95: ±360 | D95: 6.1% | E95: ±0.8 | F95: 13,338 | G95: ±833 | H95: 6.8% | I95: ±0.4 | J95: 15,363 | K95: ±857 | L95: 13.0% | M95: ±0.7 | N95: 14,455 | O95: ±963 | P95: 3.5% | Q95: ±0.2
A96: $50,000 to $99,999 | B96: 7,708 | C96: ±819 | D96: 16.9% | E96: ±1.6 | F96: 25,515 | G96: ±1,250 | H96: 13.0% | I96: ±0.6 | J96: 40,405 | K96: ±1,611 | L96: 34.2% | M96: ±1.1 | N96: 14,471 | O96: ±880 | P96: 3.5% | Q96: ±0.2
A97: $100,000 to $149,999 | B97: 7,770 | C97: ±637 | D97: 17.0% | E97: ±1.2 | F97: 31,042 | G97: ±1,254 | H97: 15.8% | I97: ±0.6 | J97: 19,678 | K97: ±1,179 | L97: 16.6% | M97: ±0.9 | N97: 39,984 | O97: ±1,443 | P97: 9.5% | Q97: ±0.3
A98: $150,000 to $199,999 | B98: 8,098 | C98: ±773 | D98: 17.7% | E98: ±1.6 | F98: 36,723 | G98: ±1,451 | H98: 18.7% | I98: ±0.7 | J98: 14,225 | K98: ±1,061 | L98: 12.0% | M98: ±0.9 | N98: 66,437 | O98: ±1,867 | P98: 15.9% | Q98: ±0.4
A99: $200,000 to $299,999 | B99: 7,828 | C99: ±712 | D99: 17.2% | E99: ±1.5 | F99: 52,076 | G99: ±2,030 | H99: 26.5% | I99: ±0.9 | J99: 13,932 | K99: ±983 | L99: 11.8% | M99: ±0.8 | N99: 131,614 | O99: ±2,619 | P99: 31.4% | Q99: ±0.5
A100: $300,000 to $499,999 | B100: 7,598 | C100: ±616 | D100: 16.7% | E100: ±1.4 | F100: 27,019 | G100: ±1,351 | H100: 13.7% | I100: ±0.7 | J100: 8,661 | K100: ±629 | L100: 7.3% | M100: ±0.5 | N100: 111,988 | O100: ±2,026 | P100: 26.7% | Q100: ±0.4
...

Sheet Data (2024)
B1: Little Rock city, Arkansas | F1: Jacksonville city, Florida | J1: Memphis city, Tennessee | N1: Virginia Beach-Chesapeake-Norfolk, VA-NC Metro Area
A2: Label | B2: Estimate | C2: Margin of Error | D2: Percent | E2: Percent Margin of Error | F2: Estimate | G2: Margin of Error | H2: Percent | I2: Percent Margin of Error | J2: Estimate | K2: Margin of Error | L2: Percent | M2: Percent Margin of Error | N2: Estimate | O2: Margin of Error | P2: Percent | Q2: Percent Margin of Error
A3: HOUSING OCCUPANCY
A4: Total housing units | B4: 99,014 | C4: ±2,978 | D4: 99,014 | E4: (X) | F4: 449,941 | G4: ±1,719 | H4: 449,941 | I4: (X) | J4: 291,759 | K4: ±3,489 | L4: 291,759 | M4: (X) | N4: 774,453 | O4: ±2,344 | P4: 774,453 | Q4: (X)
A5: Occupied housing units | B5: 88,738 | C5: ±3,214 | D5: 89.6% | E5: ±2.0 | F5: 413,620 | G5: ±4,742 | H5: 91.9% | I5: ±0.9 | J5: 250,830 | K5: ±4,397 | L5: 86.0% | M5: ±1.2 | N5: 717,911 | O5: ±5,455 | P5: 92.7% | Q5: ±0.7
A6: Vacant housing units | B6: 10,276 | C6: ±2,079 | D6: 10.4% | E6: ±2.0 | F6: 36,321 | G6: ±4,169 | H6: 8.1% | I6: ±0.9 | J6: 40,929 | K6: ±3,418 | L6: 14.0% | M6: ±1.2 | N6: 56,542 | O6: ±5,066 | P6: 7.3% | Q6: ±0.7
A7: Homeowner vacancy rate | B7: 1.2 | C7: ±0.9 | D7: (X) | E7: (X) | F7: 1.1 | G7: ±0.5 | H7: (X) | I7: (X) | J7: 0.5 | K7: ±0.4 | L7: (X) | M7: (X) | N7: 1.0 | O7: ±0.3 | P7: (X) | Q7: (X)
A8: Rental vacancy rate | B8: 7.3 | C8: ±2.3 | D8: (X) | E8: (X) | F8: 11.1 | G8: ±1.7 | H8: (X) | I8: (X) | J8: 10.1 | K8: ±1.5 | L8: (X) | M8: (X) | N8: 5.3 | O8: ±0.9 | P8: (X) | Q8: (X)
A9: UNITS IN STRUCTURE
A10: Total housing units | B10: 99,014 | C10: ±2,978 | D10: 99,014 | E10: (X) | F10: 449,941 | G10: ±1,719 | H10: 449,941 | I10: (X) | J10: 291,759 | K10: ±3,489 | L10: 291,759 | M10: (X) | N10: 774,453 | O10: ±2,344 | P10: 774,453 | Q10: (X)
A11: 1-unit, detached | B11: 60,546 | C11: ±3,120 | D11: 61.1% | E11: ±2.9 | F11: 264,174 | G11: ±6,217 | H11: 58.7% | I11: ±1.4 | J11: 174,213 | K11: ±5,001 | L11: 59.7% | M11: ±1.7 | N11: 460,510 | O11: ±7,088 | P11: 59.5% | Q11: ±0.9
A12: 1-unit, attached | B12: 1,441 | C12: ±702 | D12: 1.5% | E12: ±0.7 | F12: 26,068 | G12: ±3,381 | H12: 5.8% | I12: ±0.8 | J12: 13,411 | K12: ±2,368 | L12: 4.6% | M12: ±0.8 | N12: 93,208 | O12: ±4,866 | P12: 12.0% | Q12: ±0.6
A13: 2 units | B13: 1,940 | C13: ±813 | D13: 2.0% | E13: ±0.8 | F13: 6,506 | G13: ±1,868 | H13: 1.4% | I13: ±0.4 | J13: 6,311 | K13: ±1,494 | L13: 2.2% | M13: ±0.5 | N13: 16,844 | O13: ±2,747 | P13: 2.2% | Q13: ±0.4
A14: 3 or 4 units | B14: 5,854 | C14: ±1,919 | D14: 5.9% | E14: ±1.9 | F14: 21,354 | G14: ±3,096 | H14: 4.7% | I14: ±0.7 | J14: 17,520 | K14: ±2,599 | L14: 6.0% | M14: ±0.9 | N14: 37,209 | O14: ±3,616 | P14: 4.8% | Q14: ±0.5
A15: 5 to 9 units | B15: 8,451 | C15: ±2,170 | D15: 8.5% | E15: ±2.2 | F15: 20,160 | G15: ±3,338 | H15: 4.5% | I15: ±0.7 | J15: 24,438 | K15: ±3,111 | L15: 8.4% | M15: ±1.1 | N15: 53,063 | O15: ±4,837 | P15: 6.9% | Q15: ±0.6
A16: 10 to 19 units | B16: 7,938 | C16: ±2,032 | D16: 8.0% | E16: ±2.1 | F16: 34,964 | G16: ±5,600 | H16: 7.8% | I16: ±1.2 | J16: 21,659 | K16: ±3,317 | L16: 7.4% | M16: ±1.1 | N16: 36,336 | O16: ±3,882 | P16: 4.7% | Q16: ±0.5
A17: 20 or more units | B17: 10,607 | C17: ±1,826 | D17: 10.7% | E17: ±1.7 | F17: 60,947 | G17: ±6,382 | H17: 13.5% | I17: ±1.4 | J17: 30,583 | K17: ±3,449 | L17: 10.5% | M17: ±1.2 | N17: 57,764 | O17: ±4,796 | P17: 7.5% | Q17: ±0.6
A18: Mobile home | B18: 2,237 | C18: ±863 | D18: 2.3% | E18: ±0.9 | F18: 15,393 | G18: ±2,424 | H18: 3.4% | I18: ±0.5 | J18: 3,624 | K18: ±1,207 | L18: 1.2% | M18: ±0.4 | N18: 19,023 | O18: ±2,329 | P18: 2.5% | Q18: ±0.3
A19: Boat, RV, van, etc. | B19: 0 | C19: ±213 | D19: 0.0% | E19: ±0.2 | F19: 375 | G19: ±500 | H19: 0.1% | I19: ±0.1 | J19: 0 | K19: ±230 | L19: 0.0% | M19: ±0.1 | N19: 496 | O19: ±408 | P19: 0.1% | Q19: ±0.1
A20: YEAR STRUCTURE BUILT
A21: Total housing units | B21: 99,014 | C21: ±2,978 | D21: 99,014 | E21: (X) | F21: 449,941 | G21: ±1,719 | H21: 449,941 | I21: (X) | J21: 291,759 | K21: ±3,489 | L21: 291,759 | M21: (X) | N21: 774,453 | O21: ±2,344 | P21: 774,453 | Q21: (X)
A22: Built 2020 or later | B22: 2,288 | C22: ±1,058 | D22: 2.3% | E22: ±1.1 | F22: 39,720 | G22: ±5,026 | H22: 8.8% | I22: ±1.1 | J22: 3,936 | K22: ±1,407 | L22: 1.3% | M22: ±0.5 | N22: 20,187 | O22: ±2,778 | P22: 2.6% | Q22: ±0.4
A23: Built 2010 to 2019 | B23: 13,117 | C23: ±2,686 | D23: 13.2% | E23: ±2.6 | F23: 55,313 | G23: ±5,836 | H23: 12.3% | I23: ±1.3 | J23: 13,814 | K23: ±2,830 | L23: 4.7% | M23: ±1.0 | N23: 78,087 | O23: ±4,686 | P23: 10.1% | Q23: ±0.6
A24: Built 2000 to 2009 | B24: 7,361 | C24: ±1,569 | D24: 7.4% | E24: ±1.5 | F24: 75,466 | G24: ±4,362 | H24: 16.8% | I24: ±1.0 | J24: 23,079 | K24: ±3,118 | L24: 7.9% | M24: ±1.1 | N24: 97,636 | O24: ±5,539 | P24: 12.6% | Q24: ±0.7
A25: Built 1990 to 1999 | B25: 11,911 | C25: ±2,408 | D25: 12.0% | E25: ±2.4 | F25: 57,027 | G25: ±4,979 | H25: 12.7% | I25: ±1.1 | J25: 24,941 | K25: ±3,090 | L25: 8.5% | M25: ±1.1 | N25: 101,693 | O25: ±4,779 | P25: 13.1% | Q25: ±0.6
A26: Built 1980 to 1989 | B26: 11,515 | C26: ±2,247 | D26: 11.6% | E26: ±2.3 | F26: 59,430 | G26: ±5,073 | H26: 13.2% | I26: ±1.1 | J26: 39,089 | K26: ±4,074 | L26: 13.4% | M26: ±1.4 | N26: 139,526 | O26: ±5,227 | P26: 18.0% | Q26: ±0.7
A27: Built 1970 to 1979 | B27: 15,893 | C27: ±2,567 | D27: 16.1% | E27: ±2.6 | F27: 52,532 | G27: ±4,765 | H27: 11.7% | I27: ±1.1 | J27: 47,846 | K27: ±4,166 | L27: 16.4% | M27: ±1.4 | N27: 102,363 | O27: ±4,482 | P27: 13.2% | Q27: ±0.6
A28: Built 1960 to 1969 | B28: 13,842 | C28: ±2,195 | D28: 14.0% | E28: ±2.2 | F28: 36,413 | G28: ±4,031 | H28: 8.1% | I28: ±0.9 | J28: 46,279 | K28: ±4,418 | L28: 15.9% | M28: ±1.5 | N28: 94,092 | O28: ±5,131 | P28: 12.1% | Q28: ±0.7
A29: Built 1950 to 1959 | B29: 9,344 | C29: ±1,591 | D29: 9.4% | E29: ±1.7 | F29: 38,951 | G29: ±2,848 | H29: 8.7% | I29: ±0.6 | J29: 49,097 | K29: ±4,137 | L29: 16.8% | M29: ±1.4 | N29: 70,970 | O29: ±4,420 | P29: 9.2% | Q29: ±0.6
A30: Built 1940 to 1949 | B30: 4,969 | C30: ±1,259 | D30: 5.0% | E30: ±1.3 | F30: 16,861 | G30: ±2,365 | H30: 3.7% | I30: ±0.5 | J30: 18,786 | K30: ±2,318 | L30: 6.4% | M30: ±0.8 | N30: 30,985 | O30: ±2,649 | P30: 4.0% | Q30: ±0.3
A31: Built 1939 or earlier | B31: 8,774 | C31: ±1,648 | D31: 8.9% | E31: ±1.7 | F31: 18,228 | G31: ±2,478 | H31: 4.1% | I31: ±0.6 | J31: 24,892 | K31: ±2,417 | L31: 8.5% | M31: ±0.8 | N31: 38,914 | O31: ±2,825 | P31: 5.0% | Q31: ±0.4
A32: ROOMS
A33: Total housing units | B33: 99,014 | C33: ±2,978 | D33: 99,014 | E33: (X) | F33: 449,941 | G33: ±1,719 | H33: 449,941 | I33: (X) | J33: 291,759 | K33: ±3,489 | L33: 291,759 | M33: (X) | N33: 774,453 | O33: ±2,344 | P33: 774,453 | Q33: (X)
A34: 1 room | B34: 1,970 | C34: ±901 | D34: 2.0% | E34: ±0.9 | F34: 11,247 | G34: ±2,623 | H34: 2.5% | I34: ±0.6 | J34: 7,482 | K34: ±1,870 | L34: 2.6% | M34: ±0.6 | N34: 9,462 | O34: ±2,112 | P34: 1.2% | Q34: ±0.3
A35: 2 rooms | B35: 4,523 | C35: ±1,540 | D35: 4.6% | E35: ±1.5 | F35: 13,814 | G35: ±2,564 | H35: 3.1% | I35: ±0.6 | J35: 5,029 | K35: ±1,357 | L35: 1.7% | M35: ±0.5 | N35: 15,236 | O35: ±2,064 | P35: 2.0% | Q35: ±0.3
A36: 3 rooms | B36: 10,039 | C36: ±2,018 | D36: 10.1% | E36: ±1.9 | F36: 42,842 | G36: ±4,869 | H36: 9.5% | I36: ±1.1 | J36: 27,614 | K36: ±3,618 | L36: 9.5% | M36: ±1.2 | N36: 52,323 | O36: ±4,127 | P36: 6.8% | Q36: ±0.5
A37: 4 rooms | B37: 17,518 | C37: ±2,673 | D37: 17.7% | E37: ±2.7 | F37: 84,542 | G37: ±6,705 | H37: 18.8% | I37: ±1.5 | J37: 48,197 | K37: ±3,749 | L37: 16.5% | M37: ±1.3 | N37: 113,858 | O37: ±6,227 | P37: 14.7% | Q37: ±0.8
A38: 5 rooms | B38: 19,513 | C38: ±2,691 | D38: 19.7% | E38: ±2.6 | F38: 80,514 | G38: ±5,587 | H38: 17.9% | I38: ±1.3 | J38: 68,128 | K38: ±4,886 | L38: 23.4% | M38: ±1.7 | N38: 127,996 | O38: ±7,071 | P38: 16.5% | Q38: ±0.9
A39: 6 rooms | B39: 16,278 | C39: ±2,256 | D39: 16.4% | E39: ±2.3 | F39: 87,333 | G39: ±7,079 | H39: 19.4% | I39: ±1.6 | J39: 58,141 | K39: ±4,791 | L39: 19.9% | M39: ±1.6 | N39: 133,876 | O39: ±6,100 | P39: 17.3% | Q39: ±0.8
A40: 7 rooms | B40: 11,127 | C40: ±1,890 | D40: 11.2% | E40: ±1.9 | F40: 52,584 | G40: ±4,286 | H40: 11.7% | I40: ±1.0 | J40: 32,918 | K40: ±3,335 | L40: 11.3% | M40: ±1.1 | N40: 101,764 | O40: ±4,177 | P40: 13.1% | Q40: ±0.5
A41: 8 rooms | B41: 7,808 | C41: ±1,489 | D41: 7.9% | E41: ±1.5 | F41: 41,612 | G41: ±3,734 | H41: 9.2% | I41: ±0.8 | J41: 20,190 | K41: ±2,377 | L41: 6.9% | M41: ±0.8 | N41: 96,277 | O41: ±5,179 | P41: 12.4% | Q41: ±0.7
A42: 9 rooms or more | B42: 10,238 | C42: ±1,692 | D42: 10.3% | E42: ±1.7 | F42: 35,453 | G42: ±3,496 | H42: 7.9% | I42: ±0.8 | J42: 24,060 | K42: ±2,876 | L42: 8.2% | M42: ±1.0 | N42: 123,661 | O42: ±4,621 | P42: 16.0% | Q42: ±0.6
A43: Median rooms | B43: 5.3 | C43: ±0.2 | D43: (X) | E43: (X) | F43: 5.4 | G43: ±0.1 | H43: (X) | I43: (X) | J43: 5.3 | K43: ±0.2 | L43: (X) | M43: (X) | N43: 6.0 | O43: ±0.1 | P43: (X) | Q43: (X)
A44: BEDROOMS
A45: Total housing units | B45: 99,014 | C45: ±2,978 | D45: 99,014 | E45: (X) | F45: 449,941 | G45: ±1,719 | H45: 449,941 | I45: (X) | J45: 291,759 | K45: ±3,489 | L45: 291,759 | M45: (X) | N45: 774,453 | O45: ±2,344 | P45: 774,453 | Q45: (X)
A46: No bedroom | B46: 2,428 | C46: ±1,014 | D46: 2.5% | E46: ±1.0 | F46: 12,320 | G46: ±2,883 | H46: 2.7% | I46: ±0.6 | J46: 7,605 | K46: ±1,856 | L46: 2.6% | M46: ±0.6 | N46: 11,062 | O46: ±2,081 | P46: 1.4% | Q46: ±0.3
A47: 1 bedroom | B47: 15,809 | C47: ±2,687 | D47: 16.0% | E47: ±2.5 | F47: 54,454 | G47: ±5,121 | H47: 12.1% | I47: ±1.1 | J47: 33,214 | K47: ±3,386 | L47: 11.4% | M47: ±1.1 | N47: 62,344 | O47: ±4,369 | P47: 8.1% | Q47: ±0.6
A48: 2 bedrooms | B48: 22,371 | C48: ±2,855 | D48: 22.6% | E48: ±2.8 | F48: 104,407 | G48: ±6,597 | H48: 23.2% | I48: ±1.5 | J48: 86,109 | K48: ±5,370 | L48: 29.5% | M48: ±1.7 | N48: 180,923 | O48: ±7,130 | P48: 23.4% | Q48: ±0.9
A49: 3 bedrooms | B49: 40,345 | C49: ±2,981 | D49: 40.7% | E49: ±3.0 | F49: 188,890 | G49: ±7,014 | H49: 42.0% | I49: ±1.6 | J49: 119,752 | K49: ±5,561 | L49: 41.0% | M49: ±1.9 | N49: 299,869 | O49: ±7,272 | P49: 38.7% | Q49: ±0.9
A50: 4 bedrooms | B50: 14,642 | C50: ±1,973 | D50: 14.8% | E50: ±2.0 | F50: 76,571 | G50: ±4,539 | H50: 17.0% | I50: ±1.0 | J50: 36,999 | K50: ±3,405 | L50: 12.7% | M50: ±1.2 | N50: 171,197 | O50: ±5,499 | P50: 22.1% | Q50: ±0.7
A51: 5 or more bedrooms | B51: 3,419 | C51: ±939 | D51: 3.5% | E51: ±0.9 | F51: 13,299 | G51: ±2,281 | H51: 3.0% | I51: ±0.5 | J51: 8,080 | K51: ±1,674 | L51: 2.8% | M51: ±0.6 | N51: 49,058 | O51: ±3,847 | P51: 6.3% | Q51: ±0.5
A52: HOUSING TENURE
A53: Occupied housing units | B53: 88,738 | C53: ±3,214 | D53: 88,738 | E53: (X) | F53: 413,620 | G53: ±4,742 | H53: 413,620 | I53: (X) | J53: 250,830 | K53: ±4,397 | L53: 250,830 | M53: (X) | N53: 717,911 | O53: ±5,455 | P53: 717,911 | Q53: (X)
A54: Owner-occupied | B54: 47,340 | C54: ±3,245 | D54: 53.3% | E54: ±3.2 | F54: 240,209 | G54: ±6,346 | H54: 58.1% | I54: ±1.6 | J54: 111,737 | K54: ±4,092 | L54: 44.5% | M54: ±1.5 | N54: 451,287 | O54: ±7,983 | P54: 62.9% | Q54: ±1.0
A55: Renter-occupied | B55: 41,398 | C55: ±3,265 | D55: 46.7% | E55: ±3.2 | F55: 173,411 | G55: ±7,223 | H55: 41.9% | I55: ±1.6 | J55: 139,093 | K55: ±4,742 | L55: 55.5% | M55: ±1.5 | N55: 266,624 | O55: ±7,499 | P55: 37.1% | Q55: ±1.0
A56: Average household size of owner-occupied unit | B56: 2.43 | C56: ±0.12 | D56: (X) | E56: (X) | F56: 2.56 | G56: ±0.05 | H56: (X) | I56: (X) | J56: 2.44 | K56: ±0.10 | L56: (X) | M56: (X) | N56: 2.56 | O56: ±0.03 | P56: (X) | Q56: (X)
A57: Average household size of renter-occupied unit | B57: 2.04 | C57: ±0.14 | D57: (X) | E57: (X) | F57: 2.16 | G57: ±0.08 | H57: (X) | I57: (X) | J57: 2.34 | K57: ±0.09 | L57: (X) | M57: (X) | N57: 2.21 | O57: ±0.05 | P57: (X) | Q57: (X)
A58: YEAR HOUSEHOLDER MOVED INTO UNIT
A59: Occupied housing units | B59: 88,738 | C59: ±3,214 | D59: 88,738 | E59: (X) | F59: 413,620 | G59: ±4,742 | H59: 413,620 | I59: (X) | J59: 250,830 | K59: ±4,397 | L59: 250,830 | M59: (X) | N59: 717,911 | O59: ±5,455 | P59: 717,911 | Q59: (X)
A60: Moved in 2023 or later | B60: 22,605 | C60: ±3,112 | D60: 25.5% | E60: ±3.3 | F60: 98,942 | G60: ±7,528 | H60: 23.9% | I60: ±1.7 | J60: 58,626 | K60: ±4,442 | L60: 23.4% | M60: ±1.7 | N60: 138,019 | O60: ±5,792 | P60: 19.2% | Q60: ±0.8
A61: Moved in 2020 to 2022 | B61: 20,686 | C61: ±2,574 | D61: 23.3% | E61: ±2.8 | F61: 103,960 | G61: ±6,262 | H61: 25.1% | I61: ±1.5 | J61: 59,339 | K61: ±4,759 | L61: 23.7% | M61: ±1.9 | N61: 166,296 | O61: ±6,015 | P61: 23.2% | Q61: ±0.8
A62: Moved in 2010 to 2019 | B62: 24,174 | C62: ±2,768 | D62: 27.2% | E62: ±3.0 | F62: 107,780 | G62: ±7,361 | H62: 26.1% | I62: ±1.8 | J62: 66,034 | K62: ±4,840 | L62: 26.3% | M62: ±1.8 | N62: 203,414 | O62: ±6,414 | P62: 28.3% | Q62: ±0.9
A63: Moved in 2000 to 2009 | B63: 9,805 | C63: ±1,806 | D63: 11.0% | E63: ±2.0 | F63: 50,686 | G63: ±4,084 | H63: 12.3% | I63: ±1.0 | J63: 27,837 | K63: ±2,993 | L63: 11.1% | M63: ±1.2 | N63: 88,130 | O63: ±4,194 | P63: 12.3% | Q63: ±0.6
A64: Moved in 1990 to 1999 | B64: 6,684 | C64: ±1,227 | D64: 7.5% | E64: ±1.3 | F64: 28,815 | G64: ±2,670 | H64: 7.0% | I64: ±0.6 | J64: 18,016 | K64: ±2,185 | L64: 7.2% | M64: ±0.9 | N64: 61,185 | O64: ±3,343 | P64: 8.5% | Q64: ±0.5
A65: Moved in 1989 and earlier | B65: 4,784 | C65: ±1,076 | D65: 5.4% | E65: ±1.2 | F65: 23,437 | G65: ±2,058 | H65: 5.7% | I65: ±0.5 | J65: 20,978 | K65: ±2,362 | L65: 8.4% | M65: ±0.9 | N65: 60,867 | O65: ±3,614 | P65: 8.5% | Q65: ±0.5
A66: VEHICLES AVAILABLE
A67: Occupied housing units | B67: 88,738 | C67: ±3,214 | D67: 88,738 | E67: (X) | F67: 413,620 | G67: ±4,742 | H67: 413,620 | I67: (X) | J67: 250,830 | K67: ±4,397 | L67: 250,830 | M67: (X) | N67: 717,911 | O67: ±5,455 | P67: 717,911 | Q67: (X)
A68: No vehicles available | B68: 6,275 | C68: ±1,668 | D68: 7.1% | E68: ±1.9 | F68: 35,969 | G68: ±4,606 | H68: 8.7% | I68: ±1.1 | J68: 27,480 | K68: ±3,189 | L68: 11.0% | M68: ±1.2 | N68: 50,660 | O68: ±4,636 | P68: 7.1% | Q68: ±0.6
A69: 1 vehicle available | B69: 36,731 | C69: ±3,517 | D69: 41.4% | E69: ±3.4 | F69: 162,787 | G69: ±7,035 | H69: 39.4% | I69: ±1.6 | J69: 111,847 | K69: ±6,112 | L69: 44.6% | M69: ±2.1 | N69: 239,522 | O69: ±7,904 | P69: 33.4% | Q69: ±1.1
A70: 2 vehicles available | B70: 34,414 | C70: ±2,963 | D70: 38.8% | E70: ±3.3 | F70: 149,858 | G70: ±6,544 | H70: 36.2% | I70: ±1.6 | J70: 74,110 | K70: ±5,264 | L70: 29.5% | M70: ±2.2 | N70: 267,508 | O70: ±7,041 | P70: 37.3% | Q70: ±1.0
A71: 3 or more vehicles available | B71: 11,318 | C71: ±1,968 | D71: 12.8% | E71: ±2.2 | F71: 65,006 | G71: ±5,495 | H71: 15.7% | I71: ±1.3 | J71: 37,393 | K71: ±3,294 | L71: 14.9% | M71: ±1.3 | N71: 160,221 | O71: ±6,101 | P71: 22.3% | Q71: ±0.8
A72: HOUSE HEATING FUEL
A73: Occupied housing units | B73: N | C73: N | D73: N | E73: N | F73: 413,620 | G73: ±4,742 | H73: 413,620 | I73: (X) | J73: N | K73: N | L73: N | M73: N | N73: 717,911 | O73: ±5,455 | P73: 717,911 | Q73: (X)
A74: Utility gas | B74: N | C74: N | D74: N | E74: N | F74: 18,385 | G74: ±3,369 | H74: 4.4% | I74: ±0.8 | J74: N | K74: N | L74: N | M74: N | N74: 265,625 | O74: ±6,814 | P74: 37.0% | Q74: ±1.0
A75: Bottled or tank gas (propane, butane, etc.) | B75: N | C75: N | D75: N | E75: N | F75: 3,061 | G75: ±901 | H75: 0.7% | I75: ±0.2 | J75: N | K75: N | L75: N | M75: N | N75: 11,543 | O75: ±1,752 | P75: 1.6% | Q75: ±0.2
A76: Electricity | B76: N | C76: N | D76: N | E76: N | F76: 381,695 | G76: ±5,902 | H76: 92.3% | I76: ±0.9 | J76: N | K76: N | L76: N | M76: N | N76: 422,466 | O76: ±8,180 | P76: 58.8% | Q76: ±1.0
A77: Fuel oil, kerosene, etc. | B77: N | C77: N | D77: N | E77: N | F77: 1,574 | G77: ±1,002 | H77: 0.4% | I77: ±0.2 | J77: N | K77: N | L77: N | M77: N | N77: 8,102 | O77: ±1,311 | P77: 1.1% | Q77: ±0.2
A78: Coal or coke | B78: N | C78: N | D78: N | E78: N | F78: 0 | G78: ±247 | H78: 0.0% | I78: ±0.1 | J78: N | K78: N | L78: N | M78: N | N78: 0 | O78: ±213 | P78: 0.0% | Q78: ±0.1
A79: Wood | B79: N | C79: N | D79: N | E79: N | F79: 202 | G79: ±181 | H79: 0.0% | I79: ±0.1 | J79: N | K79: N | L79: N | M79: N | N79: 1,547 | O79: ±798 | P79: 0.2% | Q79: ±0.1
A80: Solar energy | B80: N | C80: N | D80: N | E80: N | F80: 1,067 | G80: ±623 | H80: 0.3% | I80: ±0.2 | J80: N | K80: N | L80: N | M80: N | N80: 1,730 | O80: ±790 | P80: 0.2% | Q80: ±0.1
A81: Other fuel | B81: N | C81: N | D81: N | E81: N | F81: 498 | G81: ±533 | H81: 0.1% | I81: ±0.1 | J81: N | K81: N | L81: N | M81: N | N81: 1,235 | O81: ±582 | P81: 0.2% | Q81: ±0.1
A82: No fuel used | B82: N | C82: N | D82: N | E82: N | F82: 7,138 | G82: ±1,849 | H82: 1.7% | I82: ±0.4 | J82: N | K82: N | L82: N | M82: N | N82: 5,663 | O82: ±1,244 | P82: 0.8% | Q82: ±0.2
A83: SELECTED CHARACTERISTICS
A84: Occupied housing units | B84: 88,738 | C84: ±3,214 | D84: 88,738 | E84: (X) | F84: 413,620 | G84: ±4,742 | H84: 413,620 | I84: (X) | J84: 250,830 | K84: ±4,397 | L84: 250,830 | M84: (X) | N84: 717,911 | O84: ±5,455 | P84: 717,911 | Q84: (X)
A85: Lacking complete plumbing facilities | B85: 377 | C85: ±501 | D85: 0.4% | E85: ±0.6 | F85: 2,164 | G85: ±1,003 | H85: 0.5% | I85: ±0.2 | J85: 1,251 | K85: ±725 | L85: 0.5% | M85: ±0.3 | N85: 2,226 | O85: ±933 | P85: 0.3% | Q85: ±0.1
A86: Lacking complete kitchen facilities | B86: 780 | C86: ±494 | D86: 0.9% | E86: ±0.6 | F86: 3,061 | G86: ±1,058 | H86: 0.7% | I86: ±0.3 | J86: 2,575 | K86: ±977 | L86: 1.0% | M86: ±0.4 | N86: 4,857 | O86: ±1,295 | P86: 0.7% | Q86: ±0.2
A87: No telephone service available | B87: 182 | C87: ±156 | D87: 0.2% | E87: ±0.2 | F87: 3,448 | G87: ±1,109 | H87: 0.8% | I87: ±0.3 | J87: 1,102 | K87: ±657 | L87: 0.4% | M87: ±0.3 | N87: 6,785 | O87: ±1,688 | P87: 0.9% | Q87: ±0.2
A88: OCCUPANTS PER ROOM
A89: Occupied housing units | B89: 88,738 | C89: ±3,214 | D89: 88,738 | E89: (X) | F89: 413,620 | G89: ±4,742 | H89: 413,620 | I89: (X) | J89: 250,830 | K89: ±4,397 | L89: 250,830 | M89: (X) | N89: 717,911 | O89: ±5,455 | P89: 717,911 | Q89: (X)
A90: 1.00 or less | B90: 86,712 | C90: ±3,490 | D90: 97.7% | E90: ±1.2 | F90: 398,884 | G90: ±5,538 | H90: 96.4% | I90: ±0.7 | J90: 243,366 | K90: ±4,948 | L90: 97.0% | M90: ±0.6 | N90: 708,965 | O90: ±5,668 | P90: 98.8% | Q90: ±0.2
A91: 1.01 to 1.50 | B91: 1,317 | C91: ±703 | D91: 1.5% | E91: ±0.8 | F91: 8,522 | G91: ±2,065 | H91: 2.1% | I91: ±0.5 | J91: 4,877 | K91: ±1,234 | L91: 1.9% | M91: ±0.5 | N91: 6,370 | O91: ±1,311 | P91: 0.9% | Q91: ±0.2
A92: 1.51 or more | B92: 709 | C92: ±744 | D92: 0.8% | E92: ±0.8 | F92: 6,214 | G92: ±2,294 | H92: 1.5% | I92: ±0.6 | J92: 2,587 | K92: ±980 | L92: 1.0% | M92: ±0.4 | N92: 2,576 | O92: ±974 | P92: 0.4% | Q92: ±0.1
A93: VALUE
A94: Owner-occupied units | B94: 47,340 | C94: ±3,245 | D94: 47,340 | E94: (X) | F94: 240,209 | G94: ±6,346 | H94: 240,209 | I94: (X) | J94: 111,737 | K94: ±4,092 | L94: 111,737 | M94: (X) | N94: 451,287 | O94: ±7,983 | P94: 451,287 | Q94: (X)
A95: Less than $50,000 | B95: 2,664 | C95: ±1,168 | D95: 5.6% | E95: ±2.4 | F95: 10,252 | G95: ±2,015 | H95: 4.3% | I95: ±0.9 | J95: 8,481 | K95: ±1,717 | L95: 7.6% | M95: ±1.6 | N95: 18,026 | O95: ±2,245 | P95: 4.0% | Q95: ±0.5
A96: $50,000 to $99,999 | B96: 4,381 | C96: ±1,025 | D96: 9.3% | E96: ±2.0 | F96: 7,241 | G96: ±1,218 | H96: 3.0% | I96: ±0.5 | J96: 15,517 | K96: ±2,345 | L96: 13.9% | M96: ±2.1 | N96: 6,728 | O96: ±1,856 | P96: 1.5% | Q96: ±0.4
A97: $100,000 to $149,999 | B97: 3,308 | C97: ±929 | D97: 7.0% | E97: ±1.8 | F97: 11,112 | G97: ±1,949 | H97: 4.6% | I97: ±0.8 | J97: 14,209 | K97: ±2,292 | L97: 12.7% | M97: ±1.9 | N97: 10,113 | O97: ±1,554 | P97: 2.2% | Q97: ±0.3
A98: $150,000 to $199,999 | B98: 4,848 | C98: ±1,203 | D98: 10.2% | E98: ±2.5 | F98: 16,035 | G98: ±2,308 | H98: 6.7% | I98: ±0.9 | J98: 15,068 | K98: ±2,180 | L98: 13.5% | M98: ±1.9 | N98: 23,747 | O98: ±2,345 | P98: 5.3% | Q98: ±0.5
A99: $200,000 to $299,999 | B99: 11,606 | C99: ±1,833 | D99: 24.5% | E99: ±3.4 | F99: 59,453 | G99: ±4,932 | H99: 24.8% | I99: ±1.9 | J99: 23,383 | K99: ±2,479 | L99: 20.9% | M99: ±2.1 | N99: 99,404 | O99: ±4,792 | P99: 22.0% | Q99: ±1.0
A100: $300,000 to $499,999 | B100: 13,141 | C100: ±1,911 | D100: 27.8% | E100: ±4.0 | F100: 95,467 | G100: ±5,097 | H100: 39.7% | I100: ±1.8 | J100: 23,740 | K100: ±2,499 | L100: 21.2% | M100: ±2.0 | N100: 177,670 | O100: ±6,417 | P100: 39.4% | Q100: ±1.1
...

Sheet CPI Fred Data
A1: observation_date | B1: Inflation Rate | C1: Cumulative Index | D1: CPI Index (2024=1)
A2: 36526 | B2: 3.3768573 | C2: 1 | D2: =C2/C$26 -> 0.54895164
A3: 36892 | B3: 2.8261711 | C3: =C2*(1+B3/100) -> 1.0282617 | D3: =C3/C$26 -> 0.56446595
A4: 37257 | B4: 1.5860316 | C4: =C3*(1+B4/100) -> 1.0445703 | D4: =C4/C$26 -> 0.57341856
A5: 37622 | B5: 2.270095 | C5: =C4*(1+B5/100) -> 1.068283 | D5: =C5/C$26 -> 0.58643571
A6: 37987 | B6: 2.6772367 | C6: =C5*(1+B6/100) -> 1.0968835 | D6: =C6/C$26 -> 0.60213598
A7: 38353 | B7: 3.3927468 | C7: =C6*(1+B7/100) -> 1.1340979 | D7: =C7/C$26 -> 0.62256493
A8: 38718 | B8: 3.2259441 | C8: =C7*(1+B8/100) -> 1.1706833 | D8: =C8/C$26 -> 0.64264853
A9: 39083 | B9: 2.8526725 | C9: =C8*(1+B9/100) -> 1.2040791 | D9: =C9/C$26 -> 0.66098118
A10: 39448 | B10: 3.8391003 | C10: =C9*(1+B10/100) -> 1.2503049 | D10: =C10/C$26 -> 0.68635692
A11: 39814 | B11: -0.35554627 | C11: =C10*(1+B11/100) -> 1.2458595 | D11: =C11/C$26 -> 0.6839166
A12: 40179 | B12: 1.6400434 | C12: =C11*(1+B12/100) -> 1.2662921 | D12: =C12/C$26 -> 0.69513313
A13: 40544 | B13: 3.1568416 | C13: =C12*(1+B13/100) -> 1.3062669 | D13: =C13/C$26 -> 0.71707738
A14: 40909 | B14: 2.0693373 | C14: =C13*(1+B14/100) -> 1.333298 | D14: =C14/C$26 -> 0.73191613
... A26: 45292 | B26: 2.9495252 | C26: =C25*(1+B26/100) -> 1.8216541 | D26: =C26/C$26 -> 1
